{"url":"https:\/\/bdautopay.com\/invoice\/2582570763da373a4af814500b51181f","method":"GET","isAJAX":false,"startTime":1721926181.613193988800048828125,"totalTime":13.5,"totalMemory":"1.944","segmentDuration":5,"segmentCount":3,"CI_VERSION":"4.4.3","collectors":[{"title":"Timers","titleSafe":"timers","titleDetails":"","display":[],"badgeValue":null,"isEmpty":false,"hasTabContent":false,"hasLabel":false,"icon":"","hasTimelineData":true,"timelineData":[{"name":"Bootstrap","component":"Timer","start":1721926181.6180379390716552734375,"duration":0.00302410125732421875},{"name":"Routing","component":"Timer","start":1721926181.6210629940032958984375,"duration":0.0007259845733642578125},{"name":"Before Filters","component":"Timer","start":1721926181.6219589710235595703125,"duration":0.00014209747314453125},{"name":"Controller","component":"Timer","start":1721926181.6221020221710205078125,"duration":0.00459194183349609375},{"name":"Controller Constructor","component":"Timer","start":1721926181.6221020221710205078125,"duration":0.002644062042236328125},{"name":"After Filters","component":"Timer","start":1721926181.6267011165618896484375,"duration":6.79492950439453125e-5}]},{"title":"Database","titleSafe":"database","titleDetails":"(13 total Queries, 5 of them unique across 1 Connection)","display":{"queries":[{"hover":"","class":"","duration":"0.24 ms","sql":"<strong>SELECT<\/strong> `value`\n<strong>FROM<\/strong> `options`\n<strong>WHERE<\/strong> `name` = &#039;is_maintenance_mode&#039;","trace":[{"file":"APPPATH\/system\/Database\/BaseBuilder.php:1615","function":"\u00a0\u00a0\u00a0\u00a0\u00a0\u00a0\u00a0\u00a0CodeIgniter\\Database\\BaseConnection->query()","index":"\u00a0\u00a01\u00a0\u00a0\u00a0\u00a0"},{"file":"APPPATH\/Helpers\/settings_helper.php:14","function":"\u00a0\u00a0\u00a0\u00a0\u00a0\u00a0\u00a0\u00a0CodeIgniter\\Database\\BaseBuilder->get()","index":"\u00a0\u00a02\u00a0\u00a0\u00a0\u00a0"},{"file":"APPPATH\/Controllers\/BaseController.php:76","function":"\u00a0\u00a0\u00a0\u00a0\u00a0\u00a0\u00a0\u00a0get_option()","index":"\u00a0\u00a03\u00a0\u00a0\u00a0\u00a0"},{"file":"APPPATH\/system\/CodeIgniter.php:915","function":"\u00a0\u00a0\u00a0\u00a0\u00a0\u00a0\u00a0\u00a0App\\Controllers\\BaseController->initController()","index":"\u00a0\u00a04\u00a0\u00a0\u00a0\u00a0"},{"file":"APPPATH\/system\/CodeIgniter.php:493","function":"\u00a0\u00a0\u00a0\u00a0\u00a0\u00a0\u00a0\u00a0CodeIgniter\\CodeIgniter->createController()","index":"\u00a0\u00a05\u00a0\u00a0\u00a0\u00a0"},{"file":"APPPATH\/system\/CodeIgniter.php:361","function":"\u00a0\u00a0\u00a0\u00a0\u00a0\u00a0\u00a0\u00a0CodeIgniter\\CodeIgniter->handleRequest()","index":"\u00a0\u00a06\u00a0\u00a0\u00a0\u00a0"},{"file":"FCPATH\/index.php:43","function":"\u00a0\u00a0\u00a0\u00a0\u00a0\u00a0\u00a0\u00a0CodeIgniter\\CodeIgniter->run()","index":"\u00a0\u00a07\u00a0\u00a0\u00a0\u00a0"}],"trace-file":"APPPATH\/system\/Database\/BaseBuilder.php:1615","qid":"7e7daa28d7de20cbed9792cf89d6d5e9"},{"hover":"This query was called more than once.","class":"duplicate","duration":"0.14 ms","sql":"<strong>SELECT<\/strong> `value`\n<strong>FROM<\/strong> `options`\n<strong>WHERE<\/strong> `name` = &#039;is_maintenance_mode&#039;","trace":[{"file":"APPPATH\/system\/Database\/BaseBuilder.php:1615","function":"\u00a0\u00a0\u00a0\u00a0\u00a0\u00a0\u00a0\u00a0CodeIgniter\\Database\\BaseConnection->query()","index":"\u00a0\u00a01\u00a0\u00a0\u00a0\u00a0"},{"file":"APPPATH\/Helpers\/settings_helper.php:14","function":"\u00a0\u00a0\u00a0\u00a0\u00a0\u00a0\u00a0\u00a0CodeIgniter\\Database\\BaseBuilder->get()","index":"\u00a0\u00a02\u00a0\u00a0\u00a0\u00a0"},{"file":"APPPATH\/Controllers\/BaseController.php:81","function":"\u00a0\u00a0\u00a0\u00a0\u00a0\u00a0\u00a0\u00a0get_option()","index":"\u00a0\u00a03\u00a0\u00a0\u00a0\u00a0"},{"file":"APPPATH\/system\/CodeIgniter.php:915","function":"\u00a0\u00a0\u00a0\u00a0\u00a0\u00a0\u00a0\u00a0App\\Controllers\\BaseController->initController()","index":"\u00a0\u00a04\u00a0\u00a0\u00a0\u00a0"},{"file":"APPPATH\/system\/CodeIgniter.php:493","function":"\u00a0\u00a0\u00a0\u00a0\u00a0\u00a0\u00a0\u00a0CodeIgniter\\CodeIgniter->createController()","index":"\u00a0\u00a05\u00a0\u00a0\u00a0\u00a0"},{"file":"APPPATH\/system\/CodeIgniter.php:361","function":"\u00a0\u00a0\u00a0\u00a0\u00a0\u00a0\u00a0\u00a0CodeIgniter\\CodeIgniter->handleRequest()","index":"\u00a0\u00a06\u00a0\u00a0\u00a0\u00a0"},{"file":"FCPATH\/index.php:43","function":"\u00a0\u00a0\u00a0\u00a0\u00a0\u00a0\u00a0\u00a0CodeIgniter\\CodeIgniter->run()","index":"\u00a0\u00a07\u00a0\u00a0\u00a0\u00a0"}],"trace-file":"APPPATH\/system\/Database\/BaseBuilder.php:1615","qid":"514ccbeb36de0f2a6e0b92e74171c64e"},{"hover":"This query was called more than once.","class":"duplicate","duration":"0.14 ms","sql":"<strong>SELECT<\/strong> `value`\n<strong>FROM<\/strong> `options`\n<strong>WHERE<\/strong> `name` = &#039;is_maintenance_mode&#039;","trace":[{"file":"APPPATH\/system\/Database\/BaseBuilder.php:1615","function":"\u00a0\u00a0\u00a0\u00a0\u00a0\u00a0\u00a0\u00a0CodeIgniter\\Database\\BaseConnection->query()","index":"\u00a0\u00a01\u00a0\u00a0\u00a0\u00a0"},{"file":"APPPATH\/Helpers\/settings_helper.php:14","function":"\u00a0\u00a0\u00a0\u00a0\u00a0\u00a0\u00a0\u00a0CodeIgniter\\Database\\BaseBuilder->get()","index":"\u00a0\u00a02\u00a0\u00a0\u00a0\u00a0"},{"file":"APPPATH\/Controllers\/BaseController.php:85","function":"\u00a0\u00a0\u00a0\u00a0\u00a0\u00a0\u00a0\u00a0get_option()","index":"\u00a0\u00a03\u00a0\u00a0\u00a0\u00a0"},{"file":"APPPATH\/system\/CodeIgniter.php:915","function":"\u00a0\u00a0\u00a0\u00a0\u00a0\u00a0\u00a0\u00a0App\\Controllers\\BaseController->initController()","index":"\u00a0\u00a04\u00a0\u00a0\u00a0\u00a0"},{"file":"APPPATH\/system\/CodeIgniter.php:493","function":"\u00a0\u00a0\u00a0\u00a0\u00a0\u00a0\u00a0\u00a0CodeIgniter\\CodeIgniter->createController()","index":"\u00a0\u00a05\u00a0\u00a0\u00a0\u00a0"},{"file":"APPPATH\/system\/CodeIgniter.php:361","function":"\u00a0\u00a0\u00a0\u00a0\u00a0\u00a0\u00a0\u00a0CodeIgniter\\CodeIgniter->handleRequest()","index":"\u00a0\u00a06\u00a0\u00a0\u00a0\u00a0"},{"file":"FCPATH\/index.php:43","function":"\u00a0\u00a0\u00a0\u00a0\u00a0\u00a0\u00a0\u00a0CodeIgniter\\CodeIgniter->run()","index":"\u00a0\u00a07\u00a0\u00a0\u00a0\u00a0"}],"trace-file":"APPPATH\/system\/Database\/BaseBuilder.php:1615","qid":"2933d93752a69690aec0e69539f31450"},{"hover":"","class":"","duration":"0.18 ms","sql":"<strong>SELECT<\/strong> `i`.`ids` <strong>AS<\/strong> `invoice_ids`, `i`.*, `u`.`id` <strong>AS<\/strong> `user_id`, `u`.*\n<strong>FROM<\/strong> `invoice` `i`\n<strong>LEFT<\/strong> <strong>JOIN<\/strong> `users` `u` <strong>ON<\/strong> `u`.`id` = `i`.`uid`\n<strong>WHERE<\/strong> `i`.`ids` = &#039;2582570763da373a4af814500b51181f&#039;\n<strong>AND<\/strong> `i`.`status` = 1","trace":[{"file":"APPPATH\/system\/Database\/BaseBuilder.php:1615","function":"\u00a0\u00a0\u00a0\u00a0\u00a0\u00a0\u00a0\u00a0CodeIgniter\\Database\\BaseConnection->query()","index":"\u00a0\u00a01\u00a0\u00a0\u00a0\u00a0"},{"file":"APPPATH\/Modules\/Home\/Models\/HomeModel.php:90","function":"\u00a0\u00a0\u00a0\u00a0\u00a0\u00a0\u00a0\u00a0CodeIgniter\\Database\\BaseBuilder->get()","index":"\u00a0\u00a02\u00a0\u00a0\u00a0\u00a0"},{"file":"APPPATH\/Modules\/Home\/Controllers\/HomeController.php:72","function":"\u00a0\u00a0\u00a0\u00a0\u00a0\u00a0\u00a0\u00a0Home\\Models\\HomeModel->getItem()","index":"\u00a0\u00a03\u00a0\u00a0\u00a0\u00a0"},{"file":"APPPATH\/system\/CodeIgniter.php:942","function":"\u00a0\u00a0\u00a0\u00a0\u00a0\u00a0\u00a0\u00a0Home\\Controllers\\HomeController->invoice()","index":"\u00a0\u00a04\u00a0\u00a0\u00a0\u00a0"},{"file":"APPPATH\/system\/CodeIgniter.php:502","function":"\u00a0\u00a0\u00a0\u00a0\u00a0\u00a0\u00a0\u00a0CodeIgniter\\CodeIgniter->runController()","index":"\u00a0\u00a05\u00a0\u00a0\u00a0\u00a0"},{"file":"APPPATH\/system\/CodeIgniter.php:361","function":"\u00a0\u00a0\u00a0\u00a0\u00a0\u00a0\u00a0\u00a0CodeIgniter\\CodeIgniter->handleRequest()","index":"\u00a0\u00a06\u00a0\u00a0\u00a0\u00a0"},{"file":"FCPATH\/index.php:43","function":"\u00a0\u00a0\u00a0\u00a0\u00a0\u00a0\u00a0\u00a0CodeIgniter\\CodeIgniter->run()","index":"\u00a0\u00a07\u00a0\u00a0\u00a0\u00a0"}],"trace-file":"APPPATH\/system\/Database\/BaseBuilder.php:1615","qid":"a89e770e611058591d23aab1ffc2dc01"},{"hover":"","class":"","duration":"0.1 ms","sql":"<strong>SELECT<\/strong> *\n<strong>FROM<\/strong> `brands`\n<strong>WHERE<\/strong> `uid` = &#039;1&#039;\n<strong>AND<\/strong> `id` = &#039;1&#039;","trace":[{"file":"APPPATH\/system\/Database\/BaseBuilder.php:1615","function":"\u00a0\u00a0\u00a0\u00a0\u00a0\u00a0\u00a0\u00a0CodeIgniter\\Database\\BaseConnection->query()","index":"\u00a0\u00a01\u00a0\u00a0\u00a0\u00a0"},{"file":"APPPATH\/system\/Model.php:1094","function":"\u00a0\u00a0\u00a0\u00a0\u00a0\u00a0\u00a0\u00a0CodeIgniter\\Database\\BaseBuilder->get()","index":"\u00a0\u00a02\u00a0\u00a0\u00a0\u00a0"},{"file":"APPPATH\/Helpers\/user_helper.php:430","function":"\u00a0\u00a0\u00a0\u00a0\u00a0\u00a0\u00a0\u00a0CodeIgniter\\Model->get()","index":"\u00a0\u00a03\u00a0\u00a0\u00a0\u00a0"},{"file":"APPPATH\/Modules\/Home\/Controllers\/HomeController.php:78","function":"\u00a0\u00a0\u00a0\u00a0\u00a0\u00a0\u00a0\u00a0get_brand_data()","index":"\u00a0\u00a04\u00a0\u00a0\u00a0\u00a0"},{"file":"APPPATH\/system\/CodeIgniter.php:942","function":"\u00a0\u00a0\u00a0\u00a0\u00a0\u00a0\u00a0\u00a0Home\\Controllers\\HomeController->invoice()","index":"\u00a0\u00a05\u00a0\u00a0\u00a0\u00a0"},{"file":"APPPATH\/system\/CodeIgniter.php:502","function":"\u00a0\u00a0\u00a0\u00a0\u00a0\u00a0\u00a0\u00a0CodeIgniter\\CodeIgniter->runController()","index":"\u00a0\u00a06\u00a0\u00a0\u00a0\u00a0"},{"file":"APPPATH\/system\/CodeIgniter.php:361","function":"\u00a0\u00a0\u00a0\u00a0\u00a0\u00a0\u00a0\u00a0CodeIgniter\\CodeIgniter->handleRequest()","index":"\u00a0\u00a07\u00a0\u00a0\u00a0\u00a0"},{"file":"FCPATH\/index.php:43","function":"\u00a0\u00a0\u00a0\u00a0\u00a0\u00a0\u00a0\u00a0CodeIgniter\\CodeIgniter->run()","index":"\u00a0\u00a08\u00a0\u00a0\u00a0\u00a0"}],"trace-file":"APPPATH\/system\/Database\/BaseBuilder.php:1615","qid":"c8653755e221ccc7e636a82a06c75fd9"},{"hover":"This query was called more than once.","class":"duplicate","duration":"0.09 ms","sql":"<strong>SELECT<\/strong> *\n<strong>FROM<\/strong> `brands`\n<strong>WHERE<\/strong> `uid` = &#039;1&#039;\n<strong>AND<\/strong> `id` = &#039;1&#039;","trace":[{"file":"APPPATH\/system\/Database\/BaseBuilder.php:1615","function":"\u00a0\u00a0\u00a0\u00a0\u00a0\u00a0\u00a0\u00a0CodeIgniter\\Database\\BaseConnection->query()","index":"\u00a0\u00a01\u00a0\u00a0\u00a0\u00a0"},{"file":"APPPATH\/system\/Model.php:1094","function":"\u00a0\u00a0\u00a0\u00a0\u00a0\u00a0\u00a0\u00a0CodeIgniter\\Database\\BaseBuilder->get()","index":"\u00a0\u00a02\u00a0\u00a0\u00a0\u00a0"},{"file":"APPPATH\/Helpers\/user_helper.php:430","function":"\u00a0\u00a0\u00a0\u00a0\u00a0\u00a0\u00a0\u00a0CodeIgniter\\Model->get()","index":"\u00a0\u00a03\u00a0\u00a0\u00a0\u00a0"},{"file":"APPPATH\/Modules\/Home\/Views\/invoice.php:7","function":"\u00a0\u00a0\u00a0\u00a0\u00a0\u00a0\u00a0\u00a0get_brand_data()","index":"\u00a0\u00a04\u00a0\u00a0\u00a0\u00a0"},{"file":"APPPATH\/system\/View\/View.php:228","args":["\/home\/bdautopay\/public_html\/app\/Modules\/Home\/Views\/invoice.php"],"function":"\u00a0\u00a0\u00a0\u00a0\u00a0\u00a0\u00a0\u00a0include()","index":"\u00a0\u00a05\u00a0\u00a0\u00a0\u00a0"},{"file":"APPPATH\/system\/View\/View.php:231","function":"\u00a0\u00a0\u00a0\u00a0\u00a0\u00a0\u00a0\u00a0CodeIgniter\\View\\View->CodeIgniter\\View\\{closure}","index":"\u00a0\u00a06\u00a0\u00a0\u00a0\u00a0"},{"file":"APPPATH\/system\/Common.php:1190","function":"\u00a0\u00a0\u00a0\u00a0\u00a0\u00a0\u00a0\u00a0CodeIgniter\\View\\View->render()","index":"\u00a0\u00a07\u00a0\u00a0\u00a0\u00a0"},{"file":"APPPATH\/Modules\/Home\/Controllers\/HomeController.php:135","function":"\u00a0\u00a0\u00a0\u00a0\u00a0\u00a0\u00a0\u00a0view()","index":"\u00a0\u00a08\u00a0\u00a0\u00a0\u00a0"},{"file":"APPPATH\/system\/CodeIgniter.php:942","function":"\u00a0\u00a0\u00a0\u00a0\u00a0\u00a0\u00a0\u00a0Home\\Controllers\\HomeController->invoice()","index":"\u00a0\u00a09\u00a0\u00a0\u00a0\u00a0"},{"file":"APPPATH\/system\/CodeIgniter.php:502","function":"\u00a0\u00a0\u00a0\u00a0\u00a0\u00a0\u00a0\u00a0CodeIgniter\\CodeIgniter->runController()","index":"\u00a010\u00a0\u00a0\u00a0\u00a0"},{"file":"APPPATH\/system\/CodeIgniter.php:361","function":"\u00a0\u00a0\u00a0\u00a0\u00a0\u00a0\u00a0\u00a0CodeIgniter\\CodeIgniter->handleRequest()","index":"\u00a011\u00a0\u00a0\u00a0\u00a0"},{"file":"FCPATH\/index.php:43","function":"\u00a0\u00a0\u00a0\u00a0\u00a0\u00a0\u00a0\u00a0CodeIgniter\\CodeIgniter->run()","index":"\u00a012\u00a0\u00a0\u00a0\u00a0"}],"trace-file":"APPPATH\/system\/Database\/BaseBuilder.php:1615","qid":"f0c95c84258ddc9c371c97c67ae10d1e"},{"hover":"This query was called more than once.","class":"duplicate","duration":"0.09 ms","sql":"<strong>SELECT<\/strong> *\n<strong>FROM<\/strong> `brands`\n<strong>WHERE<\/strong> `uid` = &#039;1&#039;\n<strong>AND<\/strong> `id` = &#039;1&#039;","trace":[{"file":"APPPATH\/system\/Database\/BaseBuilder.php:1615","function":"\u00a0\u00a0\u00a0\u00a0\u00a0\u00a0\u00a0\u00a0CodeIgniter\\Database\\BaseConnection->query()","index":"\u00a0\u00a01\u00a0\u00a0\u00a0\u00a0"},{"file":"APPPATH\/system\/Model.php:1094","function":"\u00a0\u00a0\u00a0\u00a0\u00a0\u00a0\u00a0\u00a0CodeIgniter\\Database\\BaseBuilder->get()","index":"\u00a0\u00a02\u00a0\u00a0\u00a0\u00a0"},{"file":"APPPATH\/Helpers\/user_helper.php:430","function":"\u00a0\u00a0\u00a0\u00a0\u00a0\u00a0\u00a0\u00a0CodeIgniter\\Model->get()","index":"\u00a0\u00a03\u00a0\u00a0\u00a0\u00a0"},{"file":"APPPATH\/Modules\/Home\/Views\/invoice.php:8","function":"\u00a0\u00a0\u00a0\u00a0\u00a0\u00a0\u00a0\u00a0get_brand_data()","index":"\u00a0\u00a04\u00a0\u00a0\u00a0\u00a0"},{"file":"APPPATH\/system\/View\/View.php:228","args":["\/home\/bdautopay\/public_html\/app\/Modules\/Home\/Views\/invoice.php"],"function":"\u00a0\u00a0\u00a0\u00a0\u00a0\u00a0\u00a0\u00a0include()","index":"\u00a0\u00a05\u00a0\u00a0\u00a0\u00a0"},{"file":"APPPATH\/system\/View\/View.php:231","function":"\u00a0\u00a0\u00a0\u00a0\u00a0\u00a0\u00a0\u00a0CodeIgniter\\View\\View->CodeIgniter\\View\\{closure}","index":"\u00a0\u00a06\u00a0\u00a0\u00a0\u00a0"},{"file":"APPPATH\/system\/Common.php:1190","function":"\u00a0\u00a0\u00a0\u00a0\u00a0\u00a0\u00a0\u00a0CodeIgniter\\View\\View->render()","index":"\u00a0\u00a07\u00a0\u00a0\u00a0\u00a0"},{"file":"APPPATH\/Modules\/Home\/Controllers\/HomeController.php:135","function":"\u00a0\u00a0\u00a0\u00a0\u00a0\u00a0\u00a0\u00a0view()","index":"\u00a0\u00a08\u00a0\u00a0\u00a0\u00a0"},{"file":"APPPATH\/system\/CodeIgniter.php:942","function":"\u00a0\u00a0\u00a0\u00a0\u00a0\u00a0\u00a0\u00a0Home\\Controllers\\HomeController->invoice()","index":"\u00a0\u00a09\u00a0\u00a0\u00a0\u00a0"},{"file":"APPPATH\/system\/CodeIgniter.php:502","function":"\u00a0\u00a0\u00a0\u00a0\u00a0\u00a0\u00a0\u00a0CodeIgniter\\CodeIgniter->runController()","index":"\u00a010\u00a0\u00a0\u00a0\u00a0"},{"file":"APPPATH\/system\/CodeIgniter.php:361","function":"\u00a0\u00a0\u00a0\u00a0\u00a0\u00a0\u00a0\u00a0CodeIgniter\\CodeIgniter->handleRequest()","index":"\u00a011\u00a0\u00a0\u00a0\u00a0"},{"file":"FCPATH\/index.php:43","function":"\u00a0\u00a0\u00a0\u00a0\u00a0\u00a0\u00a0\u00a0CodeIgniter\\CodeIgniter->run()","index":"\u00a012\u00a0\u00a0\u00a0\u00a0"}],"trace-file":"APPPATH\/system\/Database\/BaseBuilder.php:1615","qid":"110bc567be9a075a21bdbfc712a6a1e9"},{"hover":"This query was called more than once.","class":"duplicate","duration":"0.09 ms","sql":"<strong>SELECT<\/strong> *\n<strong>FROM<\/strong> `brands`\n<strong>WHERE<\/strong> `uid` = &#039;1&#039;\n<strong>AND<\/strong> `id` = &#039;1&#039;","trace":[{"file":"APPPATH\/system\/Database\/BaseBuilder.php:1615","function":"\u00a0\u00a0\u00a0\u00a0\u00a0\u00a0\u00a0\u00a0CodeIgniter\\Database\\BaseConnection->query()","index":"\u00a0\u00a01\u00a0\u00a0\u00a0\u00a0"},{"file":"APPPATH\/system\/Model.php:1094","function":"\u00a0\u00a0\u00a0\u00a0\u00a0\u00a0\u00a0\u00a0CodeIgniter\\Database\\BaseBuilder->get()","index":"\u00a0\u00a02\u00a0\u00a0\u00a0\u00a0"},{"file":"APPPATH\/Helpers\/user_helper.php:430","function":"\u00a0\u00a0\u00a0\u00a0\u00a0\u00a0\u00a0\u00a0CodeIgniter\\Model->get()","index":"\u00a0\u00a03\u00a0\u00a0\u00a0\u00a0"},{"file":"APPPATH\/Modules\/Home\/Views\/invoice.php:144","function":"\u00a0\u00a0\u00a0\u00a0\u00a0\u00a0\u00a0\u00a0get_brand_data()","index":"\u00a0\u00a04\u00a0\u00a0\u00a0\u00a0"},{"file":"APPPATH\/system\/View\/View.php:228","args":["\/home\/bdautopay\/public_html\/app\/Modules\/Home\/Views\/invoice.php"],"function":"\u00a0\u00a0\u00a0\u00a0\u00a0\u00a0\u00a0\u00a0include()","index":"\u00a0\u00a05\u00a0\u00a0\u00a0\u00a0"},{"file":"APPPATH\/system\/View\/View.php:231","function":"\u00a0\u00a0\u00a0\u00a0\u00a0\u00a0\u00a0\u00a0CodeIgniter\\View\\View->CodeIgniter\\View\\{closure}","index":"\u00a0\u00a06\u00a0\u00a0\u00a0\u00a0"},{"file":"APPPATH\/system\/Common.php:1190","function":"\u00a0\u00a0\u00a0\u00a0\u00a0\u00a0\u00a0\u00a0CodeIgniter\\View\\View->render()","index":"\u00a0\u00a07\u00a0\u00a0\u00a0\u00a0"},{"file":"APPPATH\/Modules\/Home\/Controllers\/HomeController.php:135","function":"\u00a0\u00a0\u00a0\u00a0\u00a0\u00a0\u00a0\u00a0view()","index":"\u00a0\u00a08\u00a0\u00a0\u00a0\u00a0"},{"file":"APPPATH\/system\/CodeIgniter.php:942","function":"\u00a0\u00a0\u00a0\u00a0\u00a0\u00a0\u00a0\u00a0Home\\Controllers\\HomeController->invoice()","index":"\u00a0\u00a09\u00a0\u00a0\u00a0\u00a0"},{"file":"APPPATH\/system\/CodeIgniter.php:502","function":"\u00a0\u00a0\u00a0\u00a0\u00a0\u00a0\u00a0\u00a0CodeIgniter\\CodeIgniter->runController()","index":"\u00a010\u00a0\u00a0\u00a0\u00a0"},{"file":"APPPATH\/system\/CodeIgniter.php:361","function":"\u00a0\u00a0\u00a0\u00a0\u00a0\u00a0\u00a0\u00a0CodeIgniter\\CodeIgniter->handleRequest()","index":"\u00a011\u00a0\u00a0\u00a0\u00a0"},{"file":"FCPATH\/index.php:43","function":"\u00a0\u00a0\u00a0\u00a0\u00a0\u00a0\u00a0\u00a0CodeIgniter\\CodeIgniter->run()","index":"\u00a012\u00a0\u00a0\u00a0\u00a0"}],"trace-file":"APPPATH\/system\/Database\/BaseBuilder.php:1615","qid":"12836ba62168277b513cadda9a234f6d"},{"hover":"","class":"","duration":"0.12 ms","sql":"<strong>SELECT<\/strong> `value`\n<strong>FROM<\/strong> `options`\n<strong>WHERE<\/strong> `name` = &#039;business_name&#039;","trace":[{"file":"APPPATH\/system\/Database\/BaseBuilder.php:1615","function":"\u00a0\u00a0\u00a0\u00a0\u00a0\u00a0\u00a0\u00a0CodeIgniter\\Database\\BaseConnection->query()","index":"\u00a0\u00a01\u00a0\u00a0\u00a0\u00a0"},{"file":"APPPATH\/Helpers\/settings_helper.php:14","function":"\u00a0\u00a0\u00a0\u00a0\u00a0\u00a0\u00a0\u00a0CodeIgniter\\Database\\BaseBuilder->get()","index":"\u00a0\u00a02\u00a0\u00a0\u00a0\u00a0"},{"file":"APPPATH\/Modules\/Home\/Views\/invoice.php:145","function":"\u00a0\u00a0\u00a0\u00a0\u00a0\u00a0\u00a0\u00a0get_option()","index":"\u00a0\u00a03\u00a0\u00a0\u00a0\u00a0"},{"file":"APPPATH\/system\/View\/View.php:228","args":["\/home\/bdautopay\/public_html\/app\/Modules\/Home\/Views\/invoice.php"],"function":"\u00a0\u00a0\u00a0\u00a0\u00a0\u00a0\u00a0\u00a0include()","index":"\u00a0\u00a04\u00a0\u00a0\u00a0\u00a0"},{"file":"APPPATH\/system\/View\/View.php:231","function":"\u00a0\u00a0\u00a0\u00a0\u00a0\u00a0\u00a0\u00a0CodeIgniter\\View\\View->CodeIgniter\\View\\{closure}","index":"\u00a0\u00a05\u00a0\u00a0\u00a0\u00a0"},{"file":"APPPATH\/system\/Common.php:1190","function":"\u00a0\u00a0\u00a0\u00a0\u00a0\u00a0\u00a0\u00a0CodeIgniter\\View\\View->render()","index":"\u00a0\u00a06\u00a0\u00a0\u00a0\u00a0"},{"file":"APPPATH\/Modules\/Home\/Controllers\/HomeController.php:135","function":"\u00a0\u00a0\u00a0\u00a0\u00a0\u00a0\u00a0\u00a0view()","index":"\u00a0\u00a07\u00a0\u00a0\u00a0\u00a0"},{"file":"APPPATH\/system\/CodeIgniter.php:942","function":"\u00a0\u00a0\u00a0\u00a0\u00a0\u00a0\u00a0\u00a0Home\\Controllers\\HomeController->invoice()","index":"\u00a0\u00a08\u00a0\u00a0\u00a0\u00a0"},{"file":"APPPATH\/system\/CodeIgniter.php:502","function":"\u00a0\u00a0\u00a0\u00a0\u00a0\u00a0\u00a0\u00a0CodeIgniter\\CodeIgniter->runController()","index":"\u00a0\u00a09\u00a0\u00a0\u00a0\u00a0"},{"file":"APPPATH\/system\/CodeIgniter.php:361","function":"\u00a0\u00a0\u00a0\u00a0\u00a0\u00a0\u00a0\u00a0CodeIgniter\\CodeIgniter->handleRequest()","index":"\u00a010\u00a0\u00a0\u00a0\u00a0"},{"file":"FCPATH\/index.php:43","function":"\u00a0\u00a0\u00a0\u00a0\u00a0\u00a0\u00a0\u00a0CodeIgniter\\CodeIgniter->run()","index":"\u00a011\u00a0\u00a0\u00a0\u00a0"}],"trace-file":"APPPATH\/system\/Database\/BaseBuilder.php:1615","qid":"75b4c6c55b75adff2a127107a7c42ca4"},{"hover":"This query was called more than once.","class":"duplicate","duration":"0.09 ms","sql":"<strong>SELECT<\/strong> *\n<strong>FROM<\/strong> `brands`\n<strong>WHERE<\/strong> `uid` = &#039;1&#039;\n<strong>AND<\/strong> `id` = &#039;1&#039;","trace":[{"file":"APPPATH\/system\/Database\/BaseBuilder.php:1615","function":"\u00a0\u00a0\u00a0\u00a0\u00a0\u00a0\u00a0\u00a0CodeIgniter\\Database\\BaseConnection->query()","index":"\u00a0\u00a01\u00a0\u00a0\u00a0\u00a0"},{"file":"APPPATH\/system\/Model.php:1094","function":"\u00a0\u00a0\u00a0\u00a0\u00a0\u00a0\u00a0\u00a0CodeIgniter\\Database\\BaseBuilder->get()","index":"\u00a0\u00a02\u00a0\u00a0\u00a0\u00a0"},{"file":"APPPATH\/Helpers\/user_helper.php:430","function":"\u00a0\u00a0\u00a0\u00a0\u00a0\u00a0\u00a0\u00a0CodeIgniter\\Model->get()","index":"\u00a0\u00a03\u00a0\u00a0\u00a0\u00a0"},{"file":"APPPATH\/Modules\/Home\/Views\/invoice.php:176","function":"\u00a0\u00a0\u00a0\u00a0\u00a0\u00a0\u00a0\u00a0get_brand_data()","index":"\u00a0\u00a04\u00a0\u00a0\u00a0\u00a0"},{"file":"APPPATH\/system\/View\/View.php:228","args":["\/home\/bdautopay\/public_html\/app\/Modules\/Home\/Views\/invoice.php"],"function":"\u00a0\u00a0\u00a0\u00a0\u00a0\u00a0\u00a0\u00a0include()","index":"\u00a0\u00a05\u00a0\u00a0\u00a0\u00a0"},{"file":"APPPATH\/system\/View\/View.php:231","function":"\u00a0\u00a0\u00a0\u00a0\u00a0\u00a0\u00a0\u00a0CodeIgniter\\View\\View->CodeIgniter\\View\\{closure}","index":"\u00a0\u00a06\u00a0\u00a0\u00a0\u00a0"},{"file":"APPPATH\/system\/Common.php:1190","function":"\u00a0\u00a0\u00a0\u00a0\u00a0\u00a0\u00a0\u00a0CodeIgniter\\View\\View->render()","index":"\u00a0\u00a07\u00a0\u00a0\u00a0\u00a0"},{"file":"APPPATH\/Modules\/Home\/Controllers\/HomeController.php:135","function":"\u00a0\u00a0\u00a0\u00a0\u00a0\u00a0\u00a0\u00a0view()","index":"\u00a0\u00a08\u00a0\u00a0\u00a0\u00a0"},{"file":"APPPATH\/system\/CodeIgniter.php:942","function":"\u00a0\u00a0\u00a0\u00a0\u00a0\u00a0\u00a0\u00a0Home\\Controllers\\HomeController->invoice()","index":"\u00a0\u00a09\u00a0\u00a0\u00a0\u00a0"},{"file":"APPPATH\/system\/CodeIgniter.php:502","function":"\u00a0\u00a0\u00a0\u00a0\u00a0\u00a0\u00a0\u00a0CodeIgniter\\CodeIgniter->runController()","index":"\u00a010\u00a0\u00a0\u00a0\u00a0"},{"file":"APPPATH\/system\/CodeIgniter.php:361","function":"\u00a0\u00a0\u00a0\u00a0\u00a0\u00a0\u00a0\u00a0CodeIgniter\\CodeIgniter->handleRequest()","index":"\u00a011\u00a0\u00a0\u00a0\u00a0"},{"file":"FCPATH\/index.php:43","function":"\u00a0\u00a0\u00a0\u00a0\u00a0\u00a0\u00a0\u00a0CodeIgniter\\CodeIgniter->run()","index":"\u00a012\u00a0\u00a0\u00a0\u00a0"}],"trace-file":"APPPATH\/system\/Database\/BaseBuilder.php:1615","qid":"4464b06de25f428dc3e1156c2e489133"},{"hover":"","class":"","duration":"0.11 ms","sql":"<strong>SELECT<\/strong> `value`\n<strong>FROM<\/strong> `options`\n<strong>WHERE<\/strong> `name` = &#039;currency_symbol&#039;","trace":[{"file":"APPPATH\/system\/Database\/BaseBuilder.php:1615","function":"\u00a0\u00a0\u00a0\u00a0\u00a0\u00a0\u00a0\u00a0CodeIgniter\\Database\\BaseConnection->query()","index":"\u00a0\u00a01\u00a0\u00a0\u00a0\u00a0"},{"file":"APPPATH\/Helpers\/settings_helper.php:14","function":"\u00a0\u00a0\u00a0\u00a0\u00a0\u00a0\u00a0\u00a0CodeIgniter\\Database\\BaseBuilder->get()","index":"\u00a0\u00a02\u00a0\u00a0\u00a0\u00a0"},{"file":"APPPATH\/Modules\/Home\/Views\/invoice.php:206","function":"\u00a0\u00a0\u00a0\u00a0\u00a0\u00a0\u00a0\u00a0get_option()","index":"\u00a0\u00a03\u00a0\u00a0\u00a0\u00a0"},{"file":"APPPATH\/system\/View\/View.php:228","args":["\/home\/bdautopay\/public_html\/app\/Modules\/Home\/Views\/invoice.php"],"function":"\u00a0\u00a0\u00a0\u00a0\u00a0\u00a0\u00a0\u00a0include()","index":"\u00a0\u00a04\u00a0\u00a0\u00a0\u00a0"},{"file":"APPPATH\/system\/View\/View.php:231","function":"\u00a0\u00a0\u00a0\u00a0\u00a0\u00a0\u00a0\u00a0CodeIgniter\\View\\View->CodeIgniter\\View\\{closure}","index":"\u00a0\u00a05\u00a0\u00a0\u00a0\u00a0"},{"file":"APPPATH\/system\/Common.php:1190","function":"\u00a0\u00a0\u00a0\u00a0\u00a0\u00a0\u00a0\u00a0CodeIgniter\\View\\View->render()","index":"\u00a0\u00a06\u00a0\u00a0\u00a0\u00a0"},{"file":"APPPATH\/Modules\/Home\/Controllers\/HomeController.php:135","function":"\u00a0\u00a0\u00a0\u00a0\u00a0\u00a0\u00a0\u00a0view()","index":"\u00a0\u00a07\u00a0\u00a0\u00a0\u00a0"},{"file":"APPPATH\/system\/CodeIgniter.php:942","function":"\u00a0\u00a0\u00a0\u00a0\u00a0\u00a0\u00a0\u00a0Home\\Controllers\\HomeController->invoice()","index":"\u00a0\u00a08\u00a0\u00a0\u00a0\u00a0"},{"file":"APPPATH\/system\/CodeIgniter.php:502","function":"\u00a0\u00a0\u00a0\u00a0\u00a0\u00a0\u00a0\u00a0CodeIgniter\\CodeIgniter->runController()","index":"\u00a0\u00a09\u00a0\u00a0\u00a0\u00a0"},{"file":"APPPATH\/system\/CodeIgniter.php:361","function":"\u00a0\u00a0\u00a0\u00a0\u00a0\u00a0\u00a0\u00a0CodeIgniter\\CodeIgniter->handleRequest()","index":"\u00a010\u00a0\u00a0\u00a0\u00a0"},{"file":"FCPATH\/index.php:43","function":"\u00a0\u00a0\u00a0\u00a0\u00a0\u00a0\u00a0\u00a0CodeIgniter\\CodeIgniter->run()","index":"\u00a011\u00a0\u00a0\u00a0\u00a0"}],"trace-file":"APPPATH\/system\/Database\/BaseBuilder.php:1615","qid":"ee1e0704da6f9925943f258103feb030"},{"hover":"This query was called more than once.","class":"duplicate","duration":"0.11 ms","sql":"<strong>SELECT<\/strong> `value`\n<strong>FROM<\/strong> `options`\n<strong>WHERE<\/strong> `name` = &#039;currency_symbol&#039;","trace":[{"file":"APPPATH\/system\/Database\/BaseBuilder.php:1615","function":"\u00a0\u00a0\u00a0\u00a0\u00a0\u00a0\u00a0\u00a0CodeIgniter\\Database\\BaseConnection->query()","index":"\u00a0\u00a01\u00a0\u00a0\u00a0\u00a0"},{"file":"APPPATH\/Helpers\/settings_helper.php:14","function":"\u00a0\u00a0\u00a0\u00a0\u00a0\u00a0\u00a0\u00a0CodeIgniter\\Database\\BaseBuilder->get()","index":"\u00a0\u00a02\u00a0\u00a0\u00a0\u00a0"},{"file":"APPPATH\/Modules\/Home\/Views\/invoice.php:207","function":"\u00a0\u00a0\u00a0\u00a0\u00a0\u00a0\u00a0\u00a0get_option()","index":"\u00a0\u00a03\u00a0\u00a0\u00a0\u00a0"},{"file":"APPPATH\/system\/View\/View.php:228","args":["\/home\/bdautopay\/public_html\/app\/Modules\/Home\/Views\/invoice.php"],"function":"\u00a0\u00a0\u00a0\u00a0\u00a0\u00a0\u00a0\u00a0include()","index":"\u00a0\u00a04\u00a0\u00a0\u00a0\u00a0"},{"file":"APPPATH\/system\/View\/View.php:231","function":"\u00a0\u00a0\u00a0\u00a0\u00a0\u00a0\u00a0\u00a0CodeIgniter\\View\\View->CodeIgniter\\View\\{closure}","index":"\u00a0\u00a05\u00a0\u00a0\u00a0\u00a0"},{"file":"APPPATH\/system\/Common.php:1190","function":"\u00a0\u00a0\u00a0\u00a0\u00a0\u00a0\u00a0\u00a0CodeIgniter\\View\\View->render()","index":"\u00a0\u00a06\u00a0\u00a0\u00a0\u00a0"},{"file":"APPPATH\/Modules\/Home\/Controllers\/HomeController.php:135","function":"\u00a0\u00a0\u00a0\u00a0\u00a0\u00a0\u00a0\u00a0view()","index":"\u00a0\u00a07\u00a0\u00a0\u00a0\u00a0"},{"file":"APPPATH\/system\/CodeIgniter.php:942","function":"\u00a0\u00a0\u00a0\u00a0\u00a0\u00a0\u00a0\u00a0Home\\Controllers\\HomeController->invoice()","index":"\u00a0\u00a08\u00a0\u00a0\u00a0\u00a0"},{"file":"APPPATH\/system\/CodeIgniter.php:502","function":"\u00a0\u00a0\u00a0\u00a0\u00a0\u00a0\u00a0\u00a0CodeIgniter\\CodeIgniter->runController()","index":"\u00a0\u00a09\u00a0\u00a0\u00a0\u00a0"},{"file":"APPPATH\/system\/CodeIgniter.php:361","function":"\u00a0\u00a0\u00a0\u00a0\u00a0\u00a0\u00a0\u00a0CodeIgniter\\CodeIgniter->handleRequest()","index":"\u00a010\u00a0\u00a0\u00a0\u00a0"},{"file":"FCPATH\/index.php:43","function":"\u00a0\u00a0\u00a0\u00a0\u00a0\u00a0\u00a0\u00a0CodeIgniter\\CodeIgniter->run()","index":"\u00a011\u00a0\u00a0\u00a0\u00a0"}],"trace-file":"APPPATH\/system\/Database\/BaseBuilder.php:1615","qid":"18ce5579f3a50232a8f65abb85ba1fc8"},{"hover":"This query was called more than once.","class":"duplicate","duration":"0.11 ms","sql":"<strong>SELECT<\/strong> `value`\n<strong>FROM<\/strong> `options`\n<strong>WHERE<\/strong> `name` = &#039;currency_symbol&#039;","trace":[{"file":"APPPATH\/system\/Database\/BaseBuilder.php:1615","function":"\u00a0\u00a0\u00a0\u00a0\u00a0\u00a0\u00a0\u00a0CodeIgniter\\Database\\BaseConnection->query()","index":"\u00a0\u00a01\u00a0\u00a0\u00a0\u00a0"},{"file":"APPPATH\/Helpers\/settings_helper.php:14","function":"\u00a0\u00a0\u00a0\u00a0\u00a0\u00a0\u00a0\u00a0CodeIgniter\\Database\\BaseBuilder->get()","index":"\u00a0\u00a02\u00a0\u00a0\u00a0\u00a0"},{"file":"APPPATH\/Modules\/Home\/Views\/invoice.php:211","function":"\u00a0\u00a0\u00a0\u00a0\u00a0\u00a0\u00a0\u00a0get_option()","index":"\u00a0\u00a03\u00a0\u00a0\u00a0\u00a0"},{"file":"APPPATH\/system\/View\/View.php:228","args":["\/home\/bdautopay\/public_html\/app\/Modules\/Home\/Views\/invoice.php"],"function":"\u00a0\u00a0\u00a0\u00a0\u00a0\u00a0\u00a0\u00a0include()","index":"\u00a0\u00a04\u00a0\u00a0\u00a0\u00a0"},{"file":"APPPATH\/system\/View\/View.php:231","function":"\u00a0\u00a0\u00a0\u00a0\u00a0\u00a0\u00a0\u00a0CodeIgniter\\View\\View->CodeIgniter\\View\\{closure}","index":"\u00a0\u00a05\u00a0\u00a0\u00a0\u00a0"},{"file":"APPPATH\/system\/Common.php:1190","function":"\u00a0\u00a0\u00a0\u00a0\u00a0\u00a0\u00a0\u00a0CodeIgniter\\View\\View->render()","index":"\u00a0\u00a06\u00a0\u00a0\u00a0\u00a0"},{"file":"APPPATH\/Modules\/Home\/Controllers\/HomeController.php:135","function":"\u00a0\u00a0\u00a0\u00a0\u00a0\u00a0\u00a0\u00a0view()","index":"\u00a0\u00a07\u00a0\u00a0\u00a0\u00a0"},{"file":"APPPATH\/system\/CodeIgniter.php:942","function":"\u00a0\u00a0\u00a0\u00a0\u00a0\u00a0\u00a0\u00a0Home\\Controllers\\HomeController->invoice()","index":"\u00a0\u00a08\u00a0\u00a0\u00a0\u00a0"},{"file":"APPPATH\/system\/CodeIgniter.php:502","function":"\u00a0\u00a0\u00a0\u00a0\u00a0\u00a0\u00a0\u00a0CodeIgniter\\CodeIgniter->runController()","index":"\u00a0\u00a09\u00a0\u00a0\u00a0\u00a0"},{"file":"APPPATH\/system\/CodeIgniter.php:361","function":"\u00a0\u00a0\u00a0\u00a0\u00a0\u00a0\u00a0\u00a0CodeIgniter\\CodeIgniter->handleRequest()","index":"\u00a010\u00a0\u00a0\u00a0\u00a0"},{"file":"FCPATH\/index.php:43","function":"\u00a0\u00a0\u00a0\u00a0\u00a0\u00a0\u00a0\u00a0CodeIgniter\\CodeIgniter->run()","index":"\u00a011\u00a0\u00a0\u00a0\u00a0"}],"trace-file":"APPPATH\/system\/Database\/BaseBuilder.php:1615","qid":"14c57c1a7c68909336db1d51bcb15186"}]},"badgeValue":13,"isEmpty":false,"hasTabContent":true,"hasLabel":false,"icon":"data:image\/png;base64,iVBORw0KGgoAAAANSUhEUgAAABgAAAAYCAYAAADgdz34AAAAAXNSR0IArs4c6QAAAARnQU1BAACxjwv8YQUAAAAJcEhZcwAADsMAAA7DAcdvqGQAAADMSURBVEhLY6A3YExLSwsA4nIycQDIDIhRWEBqamo\/UNF\/SjDQjF6ocZgAKPkRiFeEhoYyQ4WIBiA9QAuWAPEHqBAmgLqgHcolGQD1V4DMgHIxwbCxYD+QBqcKINseKo6eWrBioPrtQBq\/BcgY5ht0cUIYbBg2AJKkRxCNWkDQgtFUNJwtABr+F6igE8olGQD114HMgHIxAVDyAhA\/AlpSA8RYUwoeXAPVex5qHCbIyMgwBCkAuQJIY00huDBUz\/mUlBQDqHGjgBjAwAAACexpph6oHSQAAAAASUVORK5CYII=","hasTimelineData":true,"timelineData":[{"name":"Connecting to Database: \"default\"","component":"Database","start":1721926181.6233799457550048828125,"duration":"0.000557"},{"name":"Query","component":"Database","start":1721926181.6239941120147705078125,"duration":"0.000242","query":"<strong>SELECT<\/strong> `value`\n<strong>FROM<\/strong> `options`\n<strong>WHERE<\/strong> `name` = &#039;is_maintenance_mode&#039;"},{"name":"Query","component":"Database","start":1721926181.6244029998779296875,"duration":"0.000142","query":"<strong>SELECT<\/strong> `value`\n<strong>FROM<\/strong> `options`\n<strong>WHERE<\/strong> `name` = &#039;is_maintenance_mode&#039;"},{"name":"Query","component":"Database","start":1721926181.6245830059051513671875,"duration":"0.000137","query":"<strong>SELECT<\/strong> `value`\n<strong>FROM<\/strong> `options`\n<strong>WHERE<\/strong> `name` = &#039;is_maintenance_mode&#039;"},{"name":"Query","component":"Database","start":1721926181.624990940093994140625,"duration":"0.000178","query":"<strong>SELECT<\/strong> `i`.`ids` <strong>AS<\/strong> `invoice_ids`, `i`.*, `u`.`id` <strong>AS<\/strong> `user_id`, `u`.*\n<strong>FROM<\/strong> `invoice` `i`\n<strong>LEFT<\/strong> <strong>JOIN<\/strong> `users` `u` <strong>ON<\/strong> `u`.`id` = `i`.`uid`\n<strong>WHERE<\/strong> `i`.`ids` = &#039;2582570763da373a4af814500b51181f&#039;\n<strong>AND<\/strong> `i`.`status` = 1"},{"name":"Query","component":"Database","start":1721926181.62526607513427734375,"duration":"0.000099","query":"<strong>SELECT<\/strong> *\n<strong>FROM<\/strong> `brands`\n<strong>WHERE<\/strong> `uid` = &#039;1&#039;\n<strong>AND<\/strong> `id` = &#039;1&#039;"},{"name":"Query","component":"Database","start":1721926181.62549304962158203125,"duration":"0.000092","query":"<strong>SELECT<\/strong> *\n<strong>FROM<\/strong> `brands`\n<strong>WHERE<\/strong> `uid` = &#039;1&#039;\n<strong>AND<\/strong> `id` = &#039;1&#039;"},{"name":"Query","component":"Database","start":1721926181.6256339550018310546875,"duration":"0.000090","query":"<strong>SELECT<\/strong> *\n<strong>FROM<\/strong> `brands`\n<strong>WHERE<\/strong> `uid` = &#039;1&#039;\n<strong>AND<\/strong> `id` = &#039;1&#039;"},{"name":"Query","component":"Database","start":1721926181.6257989406585693359375,"duration":"0.000091","query":"<strong>SELECT<\/strong> *\n<strong>FROM<\/strong> `brands`\n<strong>WHERE<\/strong> `uid` = &#039;1&#039;\n<strong>AND<\/strong> `id` = &#039;1&#039;"},{"name":"Query","component":"Database","start":1721926181.62594890594482421875,"duration":"0.000115","query":"<strong>SELECT<\/strong> `value`\n<strong>FROM<\/strong> `options`\n<strong>WHERE<\/strong> `name` = &#039;business_name&#039;"},{"name":"Query","component":"Database","start":1721926181.6261370182037353515625,"duration":"0.000095","query":"<strong>SELECT<\/strong> *\n<strong>FROM<\/strong> `brands`\n<strong>WHERE<\/strong> `uid` = &#039;1&#039;\n<strong>AND<\/strong> `id` = &#039;1&#039;"},{"name":"Query","component":"Database","start":1721926181.626267910003662109375,"duration":"0.000113","query":"<strong>SELECT<\/strong> `value`\n<strong>FROM<\/strong> `options`\n<strong>WHERE<\/strong> `name` = &#039;currency_symbol&#039;"},{"name":"Query","component":"Database","start":1721926181.6264131069183349609375,"duration":"0.000113","query":"<strong>SELECT<\/strong> `value`\n<strong>FROM<\/strong> `options`\n<strong>WHERE<\/strong> `name` = &#039;currency_symbol&#039;"},{"name":"Query","component":"Database","start":1721926181.626555919647216796875,"duration":"0.000112","query":"<strong>SELECT<\/strong> `value`\n<strong>FROM<\/strong> `options`\n<strong>WHERE<\/strong> `name` = &#039;currency_symbol&#039;"}]},{"title":"Logs","titleSafe":"logs","titleDetails":"","display":{"logs":[]},"badgeValue":null,"isEmpty":true,"hasTabContent":true,"hasLabel":false,"icon":"data:image\/png;base64,iVBORw0KGgoAAAANSUhEUgAAABgAAAAYCAYAAADgdz34AAAAAXNSR0IArs4c6QAAAARnQU1BAACxjwv8YQUAAAAJcEhZcwAADsMAAA7DAcdvqGQAAACYSURBVEhLYxgFJIHU1FSjtLS0i0D8AYj7gEKMEBkqAaAFF4D4ERCvAFrwH4gDoFIMKSkpFkB+OTEYqgUTACXfA\/GqjIwMQyD9H2hRHlQKJFcBEiMGQ7VgAqCBvUgK32dmZspCpagGGNPT0\/1BLqeF4bQHQJePpiIwhmrBBEADR1MRfgB0+WgqAmOoFkwANHA0FY0CUgEDAwCQ0PUpNB3kqwAAAABJRU5ErkJggg==","hasTimelineData":false,"timelineData":[]},{"title":"Views","titleSafe":"views","titleDetails":"","display":[],"badgeValue":1,"isEmpty":false,"hasTabContent":false,"hasLabel":true,"icon":"data:image\/png;base64,iVBORw0KGgoAAAANSUhEUgAAABgAAAAYCAYAAADgdz34AAAAAXNSR0IArs4c6QAAAARnQU1BAACxjwv8YQUAAAAJcEhZcwAADsMAAA7DAcdvqGQAAADeSURBVEhL7ZSxDcIwEEWNYA0YgGmgyAaJLTcUaaBzQQEVjMEabBQxAdw53zTHiThEovGTfnE\/9rsoRUxhKLOmaa6Uh7X2+UvguLCzVxN1XW9x4EYHzik033Hp3X0LO+DaQG8MDQcuq6qao4qkHuMgQggLvkPLjqh00ZgFDBacMJYFkuwFlH1mshdkZ5JPJERA9JpI6xNCBESvibQ+IURA9JpI6xNCBESvibQ+IURA9DTsuHTOrVFFxixgB\/eUFlU8uKJ0eDBFOu\/9EvoeKnlJS2\/08Tc8NOwQ8sIfMeYFjqKDjdU2sp4AAAAASUVORK5CYII=","hasTimelineData":true,"timelineData":[{"name":"View: Home\\Views\\invoice.php","component":"Views","start":1721926181.625421047210693359375,"duration":0.0012629032135009765625}]},{"title":"Files","titleSafe":"files","titleDetails":"( 161 )","display":{"coreFiles":[],"userFiles":[{"path":"APPPATH\/Config\/App.php","name":"App.php"},{"path":"APPPATH\/Config\/Autoload.php","name":"Autoload.php"},{"path":"APPPATH\/Config\/Boot\/development.php","name":"development.php"},{"path":"APPPATH\/Config\/Cache.php","name":"Cache.php"},{"path":"APPPATH\/Config\/Constants.php","name":"Constants.php"},{"path":"APPPATH\/Config\/ContentSecurityPolicy.php","name":"ContentSecurityPolicy.php"},{"path":"APPPATH\/Config\/Cookie.php","name":"Cookie.php"},{"path":"APPPATH\/Config\/Database.php","name":"Database.php"},{"path":"APPPATH\/Config\/Events.php","name":"Events.php"},{"path":"APPPATH\/Config\/Exceptions.php","name":"Exceptions.php"},{"path":"APPPATH\/Config\/Feature.php","name":"Feature.php"},{"path":"APPPATH\/Config\/Filters.php","name":"Filters.php"},{"path":"APPPATH\/Config\/Honeypot.php","name":"Honeypot.php"},{"path":"APPPATH\/Config\/Kint.php","name":"Kint.php"},{"path":"APPPATH\/Config\/Logger.php","name":"Logger.php"},{"path":"APPPATH\/Config\/Modules.php","name":"Modules.php"},{"path":"APPPATH\/Config\/Paths.php","name":"Paths.php"},{"path":"APPPATH\/Config\/Routes.php","name":"Routes.php"},{"path":"APPPATH\/Config\/Routing.php","name":"Routing.php"},{"path":"APPPATH\/Config\/Services.php","name":"Services.php"},{"path":"APPPATH\/Config\/Site_config.php","name":"Site_config.php"},{"path":"APPPATH\/Config\/Toolbar.php","name":"Toolbar.php"},{"path":"APPPATH\/Config\/UserAgents.php","name":"UserAgents.php"},{"path":"APPPATH\/Config\/Validation.php","name":"Validation.php"},{"path":"APPPATH\/Config\/View.php","name":"View.php"},{"path":"APPPATH\/Controllers\/BaseController.php","name":"BaseController.php"},{"path":"APPPATH\/Helpers\/app_helper.php","name":"app_helper.php"},{"path":"APPPATH\/Helpers\/common_helper.php","name":"common_helper.php"},{"path":"APPPATH\/Helpers\/settings_helper.php","name":"settings_helper.php"},{"path":"APPPATH\/Helpers\/user_helper.php","name":"user_helper.php"},{"path":"APPPATH\/Libraries\/GatewayApi.php","name":"GatewayApi.php"},{"path":"APPPATH\/Libraries\/Template.php","name":"Template.php"},{"path":"APPPATH\/Modules\/Admin\/Config\/Routes.php","name":"Routes.php"},{"path":"APPPATH\/Modules\/Blocks\/Config\/Routes.php","name":"Routes.php"},{"path":"APPPATH\/Modules\/Home\/Config\/Routes.php","name":"Routes.php"},{"path":"APPPATH\/Modules\/Home\/Controllers\/HomeController.php","name":"HomeController.php"},{"path":"APPPATH\/Modules\/Home\/Models\/HomeModel.php","name":"HomeModel.php"},{"path":"APPPATH\/Modules\/Home\/Views\/invoice.php","name":"invoice.php"},{"path":"APPPATH\/Modules\/Maintainance\/Config\/Routes.php","name":"Routes.php"},{"path":"APPPATH\/Modules\/User\/Config\/Routes.php","name":"Routes.php"},{"path":"APPPATH\/Modules\/User\/Models\/UserModel.php","name":"UserModel.php"},{"path":"APPPATH\/system\/API\/ResponseTrait.php","name":"ResponseTrait.php"},{"path":"APPPATH\/system\/Autoloader\/Autoloader.php","name":"Autoloader.php"},{"path":"APPPATH\/system\/Autoloader\/FileLocator.php","name":"FileLocator.php"},{"path":"APPPATH\/system\/BaseModel.php","name":"BaseModel.php"},{"path":"APPPATH\/system\/Cache\/CacheFactory.php","name":"CacheFactory.php"},{"path":"APPPATH\/system\/Cache\/CacheInterface.php","name":"CacheInterface.php"},{"path":"APPPATH\/system\/Cache\/Handlers\/BaseHandler.php","name":"BaseHandler.php"},{"path":"APPPATH\/system\/Cache\/Handlers\/FileHandler.php","name":"FileHandler.php"},{"path":"APPPATH\/system\/Cache\/ResponseCache.php","name":"ResponseCache.php"},{"path":"APPPATH\/system\/CodeIgniter.php","name":"CodeIgniter.php"},{"path":"APPPATH\/system\/Common.php","name":"Common.php"},{"path":"APPPATH\/system\/Config\/AutoloadConfig.php","name":"AutoloadConfig.php"},{"path":"APPPATH\/system\/Config\/BaseConfig.php","name":"BaseConfig.php"},{"path":"APPPATH\/system\/Config\/BaseService.php","name":"BaseService.php"},{"path":"APPPATH\/system\/Config\/DotEnv.php","name":"DotEnv.php"},{"path":"APPPATH\/system\/Config\/Factories.php","name":"Factories.php"},{"path":"APPPATH\/system\/Config\/Factory.php","name":"Factory.php"},{"path":"APPPATH\/system\/Config\/Routing.php","name":"Routing.php"},{"path":"APPPATH\/system\/Config\/Services.php","name":"Services.php"},{"path":"APPPATH\/system\/Config\/View.php","name":"View.php"},{"path":"APPPATH\/system\/Controller.php","name":"Controller.php"},{"path":"APPPATH\/system\/Cookie\/CloneableCookieInterface.php","name":"CloneableCookieInterface.php"},{"path":"APPPATH\/system\/Cookie\/Cookie.php","name":"Cookie.php"},{"path":"APPPATH\/system\/Cookie\/CookieInterface.php","name":"CookieInterface.php"},{"path":"APPPATH\/system\/Cookie\/CookieStore.php","name":"CookieStore.php"},{"path":"APPPATH\/system\/Database\/BaseBuilder.php","name":"BaseBuilder.php"},{"path":"APPPATH\/system\/Database\/BaseConnection.php","name":"BaseConnection.php"},{"path":"APPPATH\/system\/Database\/BaseResult.php","name":"BaseResult.php"},{"path":"APPPATH\/system\/Database\/Config.php","name":"Config.php"},{"path":"APPPATH\/system\/Database\/ConnectionInterface.php","name":"ConnectionInterface.php"},{"path":"APPPATH\/system\/Database\/Database.php","name":"Database.php"},{"path":"APPPATH\/system\/Database\/MySQLi\/Builder.php","name":"Builder.php"},{"path":"APPPATH\/system\/Database\/MySQLi\/Connection.php","name":"Connection.php"},{"path":"APPPATH\/system\/Database\/MySQLi\/Result.php","name":"Result.php"},{"path":"APPPATH\/system\/Database\/Query.php","name":"Query.php"},{"path":"APPPATH\/system\/Database\/QueryInterface.php","name":"QueryInterface.php"},{"path":"APPPATH\/system\/Database\/ResultInterface.php","name":"ResultInterface.php"},{"path":"APPPATH\/system\/Debug\/Exceptions.php","name":"Exceptions.php"},{"path":"APPPATH\/system\/Debug\/Timer.php","name":"Timer.php"},{"path":"APPPATH\/system\/Debug\/Toolbar.php","name":"Toolbar.php"},{"path":"APPPATH\/system\/Debug\/Toolbar\/Collectors\/BaseCollector.php","name":"BaseCollector.php"},{"path":"APPPATH\/system\/Debug\/Toolbar\/Collectors\/Database.php","name":"Database.php"},{"path":"APPPATH\/system\/Debug\/Toolbar\/Collectors\/Events.php","name":"Events.php"},{"path":"APPPATH\/system\/Debug\/Toolbar\/Collectors\/Files.php","name":"Files.php"},{"path":"APPPATH\/system\/Debug\/Toolbar\/Collectors\/Logs.php","name":"Logs.php"},{"path":"APPPATH\/system\/Debug\/Toolbar\/Collectors\/Routes.php","name":"Routes.php"},{"path":"APPPATH\/system\/Debug\/Toolbar\/Collectors\/Timers.php","name":"Timers.php"},{"path":"APPPATH\/system\/Debug\/Toolbar\/Collectors\/Views.php","name":"Views.php"},{"path":"APPPATH\/system\/Events\/Events.php","name":"Events.php"},{"path":"APPPATH\/system\/Filters\/DebugToolbar.php","name":"DebugToolbar.php"},{"path":"APPPATH\/system\/Filters\/FilterInterface.php","name":"FilterInterface.php"},{"path":"APPPATH\/system\/Filters\/Filters.php","name":"Filters.php"},{"path":"APPPATH\/system\/Filters\/Honeypot.php","name":"Honeypot.php"},{"path":"APPPATH\/system\/HTTP\/ContentSecurityPolicy.php","name":"ContentSecurityPolicy.php"},{"path":"APPPATH\/system\/HTTP\/Header.php","name":"Header.php"},{"path":"APPPATH\/system\/HTTP\/IncomingRequest.php","name":"IncomingRequest.php"},{"path":"APPPATH\/system\/HTTP\/Message.php","name":"Message.php"},{"path":"APPPATH\/system\/HTTP\/MessageInterface.php","name":"MessageInterface.php"},{"path":"APPPATH\/system\/HTTP\/MessageTrait.php","name":"MessageTrait.php"},{"path":"APPPATH\/system\/HTTP\/OutgoingRequest.php","name":"OutgoingRequest.php"},{"path":"APPPATH\/system\/HTTP\/OutgoingRequestInterface.php","name":"OutgoingRequestInterface.php"},{"path":"APPPATH\/system\/HTTP\/Request.php","name":"Request.php"},{"path":"APPPATH\/system\/HTTP\/RequestInterface.php","name":"RequestInterface.php"},{"path":"APPPATH\/system\/HTTP\/RequestTrait.php","name":"RequestTrait.php"},{"path":"APPPATH\/system\/HTTP\/Response.php","name":"Response.php"},{"path":"APPPATH\/system\/HTTP\/ResponseInterface.php","name":"ResponseInterface.php"},{"path":"APPPATH\/system\/HTTP\/ResponseTrait.php","name":"ResponseTrait.php"},{"path":"APPPATH\/system\/HTTP\/SiteURI.php","name":"SiteURI.php"},{"path":"APPPATH\/system\/HTTP\/SiteURIFactory.php","name":"SiteURIFactory.php"},{"path":"APPPATH\/system\/HTTP\/URI.php","name":"URI.php"},{"path":"APPPATH\/system\/HTTP\/UserAgent.php","name":"UserAgent.php"},{"path":"APPPATH\/system\/Helpers\/array_helper.php","name":"array_helper.php"},{"path":"APPPATH\/system\/Helpers\/cookie_helper.php","name":"cookie_helper.php"},{"path":"APPPATH\/system\/Helpers\/form_helper.php","name":"form_helper.php"},{"path":"APPPATH\/system\/Helpers\/inflector_helper.php","name":"inflector_helper.php"},{"path":"APPPATH\/system\/Helpers\/kint_helper.php","name":"kint_helper.php"},{"path":"APPPATH\/system\/Helpers\/security_helper.php","name":"security_helper.php"},{"path":"APPPATH\/system\/Helpers\/url_helper.php","name":"url_helper.php"},{"path":"APPPATH\/system\/Honeypot\/Honeypot.php","name":"Honeypot.php"},{"path":"APPPATH\/system\/I18n\/Time.php","name":"Time.php"},{"path":"APPPATH\/system\/I18n\/TimeTrait.php","name":"TimeTrait.php"},{"path":"APPPATH\/system\/Log\/Logger.php","name":"Logger.php"},{"path":"APPPATH\/system\/Model.php","name":"Model.php"},{"path":"APPPATH\/system\/Modules\/Modules.php","name":"Modules.php"},{"path":"APPPATH\/system\/Router\/AutoRouter.php","name":"AutoRouter.php"},{"path":"APPPATH\/system\/Router\/AutoRouterInterface.php","name":"AutoRouterInterface.php"},{"path":"APPPATH\/system\/Router\/RouteCollection.php","name":"RouteCollection.php"},{"path":"APPPATH\/system\/Router\/RouteCollectionInterface.php","name":"RouteCollectionInterface.php"},{"path":"APPPATH\/system\/Router\/Router.php","name":"Router.php"},{"path":"APPPATH\/system\/Router\/RouterInterface.php","name":"RouterInterface.php"},{"path":"APPPATH\/system\/Superglobals.php","name":"Superglobals.php"},{"path":"APPPATH\/system\/ThirdParty\/Escaper\/Escaper.php","name":"Escaper.php"},{"path":"APPPATH\/system\/ThirdParty\/Kint\/FacadeInterface.php","name":"FacadeInterface.php"},{"path":"APPPATH\/system\/ThirdParty\/Kint\/Kint.php","name":"Kint.php"},{"path":"APPPATH\/system\/ThirdParty\/Kint\/Renderer\/AbstractRenderer.php","name":"AbstractRenderer.php"},{"path":"APPPATH\/system\/ThirdParty\/Kint\/Renderer\/CliRenderer.php","name":"CliRenderer.php"},{"path":"APPPATH\/system\/ThirdParty\/Kint\/Renderer\/RendererInterface.php","name":"RendererInterface.php"},{"path":"APPPATH\/system\/ThirdParty\/Kint\/Renderer\/RichRenderer.php","name":"RichRenderer.php"},{"path":"APPPATH\/system\/ThirdParty\/Kint\/Renderer\/TextRenderer.php","name":"TextRenderer.php"},{"path":"APPPATH\/system\/ThirdParty\/Kint\/Utils.php","name":"Utils.php"},{"path":"APPPATH\/system\/ThirdParty\/Kint\/init.php","name":"init.php"},{"path":"APPPATH\/system\/ThirdParty\/Kint\/init_helpers.php","name":"init_helpers.php"},{"path":"APPPATH\/system\/ThirdParty\/PSR\/Log\/LogLevel.php","name":"LogLevel.php"},{"path":"APPPATH\/system\/ThirdParty\/PSR\/Log\/LoggerInterface.php","name":"LoggerInterface.php"},{"path":"APPPATH\/system\/Traits\/ConditionalTrait.php","name":"ConditionalTrait.php"},{"path":"APPPATH\/system\/Validation\/CreditCardRules.php","name":"CreditCardRules.php"},{"path":"APPPATH\/system\/Validation\/FileRules.php","name":"FileRules.php"},{"path":"APPPATH\/system\/Validation\/FormatRules.php","name":"FormatRules.php"},{"path":"APPPATH\/system\/Validation\/Rules.php","name":"Rules.php"},{"path":"APPPATH\/system\/Validation\/StrictRules\/CreditCardRules.php","name":"CreditCardRules.php"},{"path":"APPPATH\/system\/Validation\/StrictRules\/FileRules.php","name":"FileRules.php"},{"path":"APPPATH\/system\/Validation\/StrictRules\/FormatRules.php","name":"FormatRules.php"},{"path":"APPPATH\/system\/Validation\/StrictRules\/Rules.php","name":"Rules.php"},{"path":"APPPATH\/system\/Validation\/Validation.php","name":"Validation.php"},{"path":"APPPATH\/system\/Validation\/ValidationInterface.php","name":"ValidationInterface.php"},{"path":"APPPATH\/system\/View\/RendererInterface.php","name":"RendererInterface.php"},{"path":"APPPATH\/system\/View\/View.php","name":"View.php"},{"path":"APPPATH\/system\/View\/ViewDecoratorTrait.php","name":"ViewDecoratorTrait.php"},{"path":"APPPATH\/system\/bootstrap.php","name":"bootstrap.php"},{"path":"FCPATH\/index.php","name":"index.php"}]},"badgeValue":161,"isEmpty":false,"hasTabContent":true,"hasLabel":false,"icon":"data:image\/png;base64,iVBORw0KGgoAAAANSUhEUgAAABgAAAAYCAYAAADgdz34AAAAAXNSR0IArs4c6QAAAARnQU1BAACxjwv8YQUAAAAJcEhZcwAADsMAAA7DAcdvqGQAAAGBSURBVEhL7ZQ9S8NQGIVTBQUncfMfCO4uLgoKbuKQOWg+OkXERRE1IAXrIHbVDrqIDuLiJgj+gro7S3dnpfq88b1FMTE3VZx64HBzzvvZWxKnj15QCcPwCD5HUfSWR+JtzgmtsUcQBEva5IIm9SwSu+95CAWbUuy67qBa32ByZEDpIaZYZSZMjjQuPcQUq8yEyYEb8FSerYeQVGbAFzJkX1PyQWLhgCz0BxTCekC1Wp0hsa6yokzhed4oje6Iz6rlJEkyIKfUEFtITVtQdAibn5rMyaYsMS+a5wTv8qeXMhcU16QZbKgl3hbs+L4\/pnpdc87MElZgq10p5DxGdq8I7xrvUWUKvG3NbSK7ubngYzdJwSsF7TiOh9VOgfcEz1UayNe3JUPM1RWC5GXYgTfc75B4NBmXJnAtTfpABX0iPvEd9ezALwkplCFXcr9styiNOKc1RRZpaPM9tcqBwlWzGY1qPL9wjqRBgF5BH6j8HWh2S7MHlX8PrmbK+k\/8PzjOOzx1D3i1pKTTAAAAAElFTkSuQmCC","hasTimelineData":false,"timelineData":[]},{"title":"Routes","titleSafe":"routes","titleDetails":"","display":{"matchedRoute":[{"directory":"","controller":"\\Home\\Controllers\\HomeController","method":"invoice","paramCount":1,"truePCount":1,"params":[{"name":"$ids = ","value":"2582570763da373a4af814500b51181f"}]}],"routes":[{"method":"GET","route":"file-manager\/view_files\/(.*)","handler":"\\App\\Controllers\\File_manager::view_files\/$1"},{"method":"GET","route":"cron","handler":"\\App\\Controllers\\ApiController::cron"},{"method":"GET","route":"api","handler":"\\App\\Controllers\\ApiController::index"},{"method":"GET","route":"api\/device-connect","handler":"\\App\\Controllers\\ApiController::deviceConnect"},{"method":"GET","route":"api\/add-data","handler":"\\App\\Controllers\\ApiController::addMessage"},{"method":"GET","route":"sign-in","handler":"\\User\\Controllers\\AuthController::signin"},{"method":"GET","route":"auth\/google_process","handler":"\\User\\Controllers\\AuthController::google_process"},{"method":"GET","route":"sign-up","handler":"\\User\\Controllers\\AuthController::signup"},{"method":"GET","route":"two-factor","handler":"\\User\\Controllers\\AuthController::two_factor"},{"method":"GET","route":"password-reset","handler":"\\User\\Controllers\\AuthController::resetPassword"},{"method":"GET","route":"affiliates\/(.*)","handler":"\\User\\Controllers\\AuthController::affiliates\/$1"},{"method":"GET","route":"password-reset\/(.*)","handler":"\\User\\Controllers\\AuthController::checkResetPassword\/$1"},{"method":"GET","route":"activation\/(.*)","handler":"\\User\\Controllers\\AuthController::activation\/$1"},{"method":"GET","route":"user\/add_funds\/complete\/(.*)","handler":"\\User\\Controllers\\AddFunds::complete\/$1"},{"method":"GET","route":"user\/logout","handler":"\\User\\Controllers\\AuthController::logout"},{"method":"GET","route":"user","handler":"\\User\\Controllers\\AuthController::index"},{"method":"GET","route":"user\/dashboard","handler":"\\User\\Controllers\\Dashboard::index"},{"method":"GET","route":"user\/profile","handler":"\\User\\Controllers\\Settings::index"},{"method":"GET","route":"user\/add_funds","handler":"\\User\\Controllers\\AddFunds::index"},{"method":"GET","route":"user\/plans","handler":"\\User\\Controllers\\PlanController::index"},{"method":"GET","route":"user\/plan-list","handler":"\\User\\Controllers\\PlanController::list"},{"method":"GET","route":"user\/buy-plan\/(.*)","handler":"\\User\\Controllers\\PlanController::buyPlan\/$1"},{"method":"GET","route":"user\/brands","handler":"\\User\\Controllers\\MerchantController::brands"},{"method":"GET","route":"user\/brands\/update","handler":"\\User\\Controllers\\MerchantController::brandsUpdate"},{"method":"GET","route":"user\/brands\/update\/(.*)","handler":"\\User\\Controllers\\MerchantController::brandsUpdate\/$1"},{"method":"GET","route":"user\/user-settings\/(.*)","handler":"\\User\\Controllers\\MerchantController::settings\/$1"},{"method":"GET","route":"user\/devices","handler":"\\User\\Controllers\\MerchantController::devices"},{"method":"GET","route":"user\/devices\/update","handler":"\\User\\Controllers\\MerchantController::devicesUpdate"},{"method":"GET","route":"user\/invoice","handler":"\\User\\Controllers\\MerchantController::index"},{"method":"GET","route":"user\/invoice\/update","handler":"\\User\\Controllers\\MerchantController::update"},{"method":"GET","route":"user\/invoice\/update\/(.*)","handler":"\\User\\Controllers\\MerchantController::update\/$1"},{"method":"GET","route":"user\/invoice\/view\/(.*)","handler":"\\User\\Controllers\\MerchantController::view_invoice\/$1"},{"method":"GET","route":"user\/paymentlink","handler":"\\User\\Controllers\\MerchantController::paymentLink"},{"method":"GET","route":"user\/transactions","handler":"\\User\\Controllers\\Transactions::index"},{"method":"GET","route":"user\/bank_transactions","handler":"\\User\\Controllers\\Transactions::bankTrx"},{"method":"GET","route":"user\/view-transaction\/(.*)\/(.*)","handler":"\\User\\Controllers\\Transactions::trxView\/$1\/$2"},{"method":"GET","route":"user\/transactions\/add-data","handler":"\\User\\Controllers\\Transactions::addSms"},{"method":"GET","route":"user\/stored-data","handler":"\\User\\Controllers\\Transactions::storedData"},{"method":"GET","route":"user\/store_data\/delete\/(.*)","handler":"\\User\\Controllers\\Transactions::storedDatadelete\/$1"},{"method":"GET","route":"user\/affiliates","handler":"\\User\\Controllers\\Settings::affiliates"},{"method":"GET","route":"user\/addons","handler":"\\User\\Controllers\\AddonController::index"},{"method":"GET","route":"maintenance","handler":"\\Maintainance\\Controllers\\MaintainanceController::index"},{"method":"GET","route":"maintenance\/access","handler":"\\Maintainance\\Controllers\\MaintainanceController::access"},{"method":"GET","route":"user\/tickets","handler":"\\Blocks\\Controllers\\Tickets::index"},{"method":"GET","route":"user\/tickets\/add","handler":"\\Blocks\\Controllers\\Tickets::add"},{"method":"GET","route":"user\/tickets\/view\/(.*)","handler":"\\Blocks\\Controllers\\Tickets::view\/$1"},{"method":"GET","route":"admin\/tickets","handler":"\\Blocks\\Controllers\\AdminTickets::index"},{"method":"GET","route":"admin\/tickets\/edit_item_ticket_message\/(.*)","handler":"\\Blocks\\Controllers\\AdminTickets::edit_item_ticket_message\/$1"},{"method":"GET","route":"admin\/tickets\/add","handler":"\\Blocks\\Controllers\\AdminTickets::add"},{"method":"GET","route":"admin\/tickets\/view\/(.*)","handler":"\\Blocks\\Controllers\\AdminTickets::view\/$1"},{"method":"GET","route":"admin\/tickets\/change_status\/(.*)\/(.*)","handler":"\\Blocks\\Controllers\\AdminTickets::changeStatus\/$1\/$2"},{"method":"GET","route":"admin\/sign-in","handler":"\\Admin\\Controllers\\AuthController::signin"},{"method":"GET","route":"admin\/password-reset","handler":"\\Admin\\Controllers\\AuthController::resetPassword"},{"method":"GET","route":"admin\/password-reset\/(.*)","handler":"\\Admin\\Controllers\\AuthController::checkResetPassword\/$1"},{"method":"GET","route":"admin\/activation\/(.*)","handler":"\\Admin\\Controllers\\AuthController::activation\/$1"},{"method":"GET","route":"admin\/logout","handler":"\\Admin\\Controllers\\AuthController::logout"},{"method":"GET","route":"admin","handler":"\\Admin\\Controllers\\AuthController::index"},{"method":"GET","route":"admin\/permission-denied","handler":"\\Admin\\Controllers\\AdminController::permission_denied"},{"method":"GET","route":"admin\/search","handler":"\\Admin\\Controllers\\Dashboard::search"},{"method":"GET","route":"admin\/dashboard","handler":"\\Admin\\Controllers\\Dashboard::index"},{"method":"GET","route":"admin\/profile","handler":"\\Admin\\Controllers\\Settings::index"},{"method":"GET","route":"admin\/timeline\/(.*)","handler":"\\Admin\\Controllers\\StaffController::timeline\/$1"},{"method":"GET","route":"admin\/users-timeline\/(.*)","handler":"\\Admin\\Controllers\\UserController::timeline\/$1"},{"method":"GET","route":"admin\/settings","handler":"\\Admin\\Controllers\\Settings::settings"},{"method":"GET","route":"admin\/settings\/(.*)","handler":"\\Admin\\Controllers\\Settings::settings\/$1"},{"method":"GET","route":"admin\/cache-clean","handler":"\\Admin\\Controllers\\Settings::cache"},{"method":"GET","route":"admin\/backup-database","handler":"\\Admin\\Controllers\\Settings::backupDatabase"},{"method":"GET","route":"admin\/addons","handler":"\\Admin\\Controllers\\Settings::addons"},{"method":"GET","route":"admin\/addons\/update","handler":"\\Admin\\Controllers\\Settings::AddonUpdate"},{"method":"GET","route":"admin\/user-addon\/update\/(.*)","handler":"\\Admin\\Controllers\\Settings::AddonUpdate\/$1"},{"method":"GET","route":"admin\/plans","handler":"\\Admin\\Controllers\\PlanController::index"},{"method":"GET","route":"admin\/user-plan","handler":"\\Admin\\Controllers\\PlanController::userPlan"},{"method":"GET","route":"admin\/plans\/edit_user_plan\/(.*)","handler":"\\Admin\\Controllers\\PlanController::edit_user_plan\/$1"},{"method":"GET","route":"admin\/plans\/update","handler":"\\Admin\\Controllers\\PlanController::update"},{"method":"GET","route":"admin\/plans\/update\/(.*)","handler":"\\Admin\\Controllers\\PlanController::update\/$1"},{"method":"GET","route":"admin\/devices","handler":"\\Admin\\Controllers\\DeviceController::index"},{"method":"GET","route":"admin\/devices\/update\/(.*)","handler":"\\Admin\\Controllers\\DeviceController::update\/$1"},{"method":"GET","route":"admin\/devices\/delete\/(.*)","handler":"\\Admin\\Controllers\\DeviceController::delete\/$1"},{"method":"GET","route":"admin\/brands","handler":"\\Admin\\Controllers\\BrandController::index"},{"method":"GET","route":"admin\/brands\/update\/(.*)","handler":"\\Admin\\Controllers\\BrandController::update\/$1"},{"method":"GET","route":"admin\/brands\/delete\/(.*)","handler":"\\Admin\\Controllers\\BrandController::delete\/$1"},{"method":"GET","route":"admin\/coupon","handler":"\\Admin\\Controllers\\Coupon::index"},{"method":"GET","route":"admin\/coupon\/update","handler":"\\Admin\\Controllers\\Coupon::update"},{"method":"GET","route":"admin\/coupon\/update\/(.*)","handler":"\\Admin\\Controllers\\Coupon::update\/$1"},{"method":"GET","route":"admin\/blogs","handler":"\\Admin\\Controllers\\BlogController::index"},{"method":"GET","route":"admin\/blogs\/update","handler":"\\Admin\\Controllers\\BlogController::update"},{"method":"GET","route":"admin\/blogs\/update\/(.*)","handler":"\\Admin\\Controllers\\BlogController::update\/$1"},{"method":"GET","route":"admin\/faqs","handler":"\\Admin\\Controllers\\FaqsController::index"},{"method":"GET","route":"admin\/faqs\/update","handler":"\\Admin\\Controllers\\FaqsController::update"},{"method":"GET","route":"admin\/faqs\/update\/(.*)","handler":"\\Admin\\Controllers\\FaqsController::update\/$1"},{"method":"GET","route":"admin\/payments","handler":"\\Admin\\Controllers\\PaymentsController::index"},{"method":"GET","route":"admin\/payments\/update","handler":"\\Admin\\Controllers\\PaymentsController::update"},{"method":"GET","route":"admin\/payments\/update\/(.*)","handler":"\\Admin\\Controllers\\PaymentsController::update\/$1"},{"method":"GET","route":"admin\/users\/export\/(.*)","handler":"\\Admin\\Controllers\\UserController::export\/$1"},{"method":"GET","route":"admin\/users","handler":"\\Admin\\Controllers\\UserController::index"},{"method":"GET","route":"admin\/users\/update","handler":"\\Admin\\Controllers\\UserController::create"},{"method":"GET","route":"admin\/users\/update\/(.*)","handler":"\\Admin\\Controllers\\UserController::create\/$1"},{"method":"GET","route":"admin\/users\/mail\/(.*)","handler":"\\Admin\\Controllers\\UserController::mail\/$1"},{"method":"GET","route":"admin\/users\/add_funds\/(.*)","handler":"\\Admin\\Controllers\\UserController::add_funds\/$1"},{"method":"GET","route":"admin\/users\/set_password\/(.*)","handler":"\\Admin\\Controllers\\UserController::set_password\/$1"},{"method":"GET","route":"admin\/staffs\/export\/(.*)","handler":"\\Admin\\Controllers\\StaffController::export\/$1"},{"method":"GET","route":"admin\/staffs","handler":"\\Admin\\Controllers\\StaffController::index"},{"method":"GET","route":"admin\/staffs\/update","handler":"\\Admin\\Controllers\\StaffController::create"},{"method":"GET","route":"admin\/staffs\/update\/(.*)","handler":"\\Admin\\Controllers\\StaffController::create\/$1"},{"method":"GET","route":"admin\/staffs\/mail\/(.*)","handler":"\\Admin\\Controllers\\StaffController::mail\/$1"},{"method":"GET","route":"admin\/staffs\/add_funds\/(.*)","handler":"\\Admin\\Controllers\\StaffController::add_funds\/$1"},{"method":"GET","route":"admin\/staffs\/set_password\/(.*)","handler":"\\Admin\\Controllers\\StaffController::set_password\/$1"},{"method":"GET","route":"admin\/staffs-roles","handler":"\\Admin\\Controllers\\StaffController::roles"},{"method":"GET","route":"admin\/staffs\/role_permision\/(.*)\/(.*)","handler":"\\Admin\\Controllers\\StaffController::role_permision\/$1\/$2"},{"method":"GET","route":"admin\/staffs\/role_permision\/(.*)","handler":"\\Admin\\Controllers\\StaffController::role_permision\/$1"},{"method":"GET","route":"admin\/transactions","handler":"\\Admin\\Controllers\\Transactions::index"},{"method":"GET","route":"admin\/bank_transactions","handler":"\\Admin\\Controllers\\Transactions::bankTrx"},{"method":"GET","route":"admin\/view-transaction\/(.*)\/(.*)","handler":"\\Admin\\Controllers\\Transactions::trxView\/$1\/$2"},{"method":"GET","route":"admin\/transactions\/add-sms","handler":"\\Admin\\Controllers\\Transactions::addSms"},{"method":"GET","route":"\/","handler":"\\Home\\Controllers\\HomeController::index"},{"method":"GET","route":"home","handler":"\\Home\\Controllers\\HomeController::index"},{"method":"GET","route":"invoice\/(.*)","handler":"\\Home\\Controllers\\HomeController::invoice\/$1"},{"method":"GET","route":"developers","handler":"\\Home\\Controllers\\DocController::index"},{"method":"GET","route":"developers\/docs","handler":"\\Home\\Controllers\\DocController::docs"},{"method":"GET","route":"sitemap.xml","handler":"\\Home\\Controllers\\Sitemap::index"},{"method":"GET","route":"terms-condition","handler":"\\Home\\Controllers\\HomeController::terms"},{"method":"GET","route":"privacy-policy","handler":"\\Home\\Controllers\\HomeController::privacy"},{"method":"GET","route":"blogs","handler":"\\Home\\Controllers\\HomeController::blogs"},{"method":"GET","route":"blog\/(.*)","handler":"\\Home\\Controllers\\HomeController::blogSingle\/$1"},{"method":"POST","route":"upload_files","handler":"\\App\\Controllers\\File_manager::upload_files"},{"method":"POST","route":"upload_files_tiny","handler":"\\App\\Controllers\\File_manager::upload_files_tiny"},{"method":"POST","route":"api\/device-connect","handler":"\\App\\Controllers\\ApiController::deviceConnect"},{"method":"POST","route":"api\/add-data","handler":"\\App\\Controllers\\ApiController::addMessage"},{"method":"POST","route":"sign-in","handler":"\\User\\Controllers\\AuthController::attempt_signin"},{"method":"POST","route":"two-factor","handler":"\\User\\Controllers\\AuthController::two_factor"},{"method":"POST","route":"sign-up","handler":"\\User\\Controllers\\AuthController::attempt_signup"},{"method":"POST","route":"password-reset","handler":"\\User\\Controllers\\AuthController::resetPasswordMail"},{"method":"POST","route":"password-reset\/(.*)","handler":"\\User\\Controllers\\AuthController::setResetPassword\/$1"},{"method":"POST","route":"activation\/(.*)","handler":"\\User\\Controllers\\AuthController::setActivation\/$1"},{"method":"POST","route":"user\/add_funds\/complete\/(.*)","handler":"\\User\\Controllers\\AddFunds::complete\/$1"},{"method":"POST","route":"user\/dashboard-data","handler":"\\User\\Controllers\\Dashboard::dashboardData"},{"method":"POST","route":"user\/update","handler":"\\User\\Controllers\\Settings::update"},{"method":"POST","route":"user\/add_funds\/process","handler":"\\User\\Controllers\\AddFunds::process"},{"method":"POST","route":"user\/buy-plan\/(.*)","handler":"\\User\\Controllers\\PlanController::buyPlan\/$1"},{"method":"POST","route":"user\/brands\/store\/(.*)","handler":"\\User\\Controllers\\MerchantController::store\/$1"},{"method":"POST","route":"user\/brands\/reset-key\/(.*)","handler":"\\User\\Controllers\\MerchantController::resetKey\/$1"},{"method":"POST","route":"user\/user-settings\/store\/(.*)","handler":"\\User\\Controllers\\MerchantController::walletStore\/$1"},{"method":"POST","route":"user\/invoice\/change_status\/(.*)","handler":"\\User\\Controllers\\MerchantController::changeStatus\/$1"},{"method":"POST","route":"user\/invoice\/delete\/(.*)","handler":"\\User\\Controllers\\MerchantController::delete\/$1"},{"method":"POST","route":"user\/paymentLinkGenerator","handler":"\\User\\Controllers\\MerchantController::paymentLinkGenerator"},{"method":"POST","route":"user\/view-transaction\/(.*)\/(.*)","handler":"\\User\\Controllers\\Transactions::trxView\/$1\/$2"},{"method":"POST","route":"user\/transactions\/add-data","handler":"\\User\\Controllers\\Transactions::addSms"},{"method":"POST","route":"user\/store_data\/delete\/(.*)","handler":"\\User\\Controllers\\Transactions::storedDatadelete\/$1"},{"method":"POST","route":"maintenance\/access","handler":"\\Maintainance\\Controllers\\MaintainanceController::attempt_access"},{"method":"POST","route":"get_total_notifiaction_count","handler":"\\Blocks\\Controllers\\BlocksController::get_total_notifiaction_count"},{"method":"POST","route":"get_user_notifications","handler":"\\Blocks\\Controllers\\BlocksController::get_user_notifications"},{"method":"POST","route":"get_admin_notifications","handler":"\\Blocks\\Controllers\\BlocksController::get_admin_notifications"},{"method":"POST","route":"search","handler":"\\Blocks\\Controllers\\BlocksController::search"},{"method":"POST","route":"user\/tickets\/store","handler":"\\Blocks\\Controllers\\Tickets::store"},{"method":"POST","route":"user\/tickets\/view\/(.*)","handler":"\\Blocks\\Controllers\\Tickets::storeMessage\/$1"},{"method":"POST","route":"admin\/tickets\/edit_item_ticket_message\/(.*)","handler":"\\Blocks\\Controllers\\AdminTickets::storeMessage\/$1"},{"method":"POST","route":"admin\/tickets\/delete_item_ticket_message\/(.*)","handler":"\\Blocks\\Controllers\\AdminTickets::delete_item_ticket_message\/$1"},{"method":"POST","route":"admin\/tickets\/store","handler":"\\Blocks\\Controllers\\AdminTickets::store"},{"method":"POST","route":"admin\/tickets\/view\/(.*)","handler":"\\Blocks\\Controllers\\AdminTickets::storeMessage\/$1"},{"method":"POST","route":"admin\/tickets\/bulk_action\/(.*)","handler":"\\Blocks\\Controllers\\AdminTickets::bulk_action\/$1"},{"method":"POST","route":"admin\/tickets\/delete\/(.*)","handler":"\\Blocks\\Controllers\\AdminTickets::delete\/$1"},{"method":"POST","route":"admin\/users\/sendEmailsToAllUsers","handler":"\\Blocks\\Controllers\\BlocksController::sendEmailsToAllUsers"},{"method":"POST","route":"admin\/sign-in","handler":"\\Admin\\Controllers\\AuthController::attempt_signin"},{"method":"POST","route":"admin\/password-reset","handler":"\\Admin\\Controllers\\AuthController::resetPasswordMail"},{"method":"POST","route":"admin\/password-reset\/(.*)","handler":"\\Admin\\Controllers\\AuthController::setResetPassword\/$1"},{"method":"POST","route":"admin\/activation\/(.*)","handler":"\\Admin\\Controllers\\AuthController::setActivation\/$1"},{"method":"POST","route":"admin\/dashboard-data","handler":"\\Admin\\Controllers\\Dashboard::dashboardData"},{"method":"POST","route":"admin\/timeline\/(.*)","handler":"\\Admin\\Controllers\\StaffController::timeline\/$1"},{"method":"POST","route":"admin\/users-timeline\/(.*)","handler":"\\Admin\\Controllers\\UserController::timeline\/$1"},{"method":"POST","route":"admin\/settings\/store","handler":"\\Admin\\Controllers\\Settings::store"},{"method":"POST","route":"admin\/addons\/store","handler":"\\Admin\\Controllers\\Settings::addonStore"},{"method":"POST","route":"admin\/addons\/change_status\/(.*)","handler":"\\Admin\\Controllers\\Settings::change_status\/$1"},{"method":"POST","route":"admin\/addons","handler":"\\Admin\\Controllers\\Settings::addonsExtract"},{"method":"POST","route":"admin\/user-addon\/(.*)\/(.*)","handler":"\\Admin\\Controllers\\Settings::useraddon\/$1\/$2"},{"method":"POST","route":"admin\/update","handler":"\\Admin\\Controllers\\Settings::update"},{"method":"POST","route":"admin\/plans\/edit_user_plan\/(.*)","handler":"\\Admin\\Controllers\\PlanController::edit_user_plan\/$1"},{"method":"POST","route":"admin\/plans\/store","handler":"\\Admin\\Controllers\\PlanController::store"},{"method":"POST","route":"admin\/plans\/change_status\/(.*)","handler":"\\Admin\\Controllers\\PlanController::changeStatus\/$1"},{"method":"POST","route":"admin\/plans\/delete\/(.*)","handler":"\\Admin\\Controllers\\PlanController::delete\/$1"},{"method":"POST","route":"admin\/plans\/bulk_action\/(.*)","handler":"\\Admin\\Controllers\\PlanController::bulk_action\/$1"},{"method":"POST","route":"admin\/plans\/change_sort\/(.*)","handler":"\\Admin\\Controllers\\PlanController::change_sort\/$1"},{"method":"POST","route":"admin\/plans\/sortpayments","handler":"\\Admin\\Controllers\\PlanController::sortpayments"},{"method":"POST","route":"admin\/devices\/bulk_action\/(.*)","handler":"\\Admin\\Controllers\\DeviceController::bulk_action\/$1"},{"method":"POST","route":"admin\/devices\/update\/(.*)","handler":"\\Admin\\Controllers\\DeviceController::update\/$1"},{"method":"POST","route":"admin\/devices\/delete\/(.*)","handler":"\\Admin\\Controllers\\DeviceController::delete\/$1"},{"method":"POST","route":"admin\/brands\/change_status\/(.*)","handler":"\\Admin\\Controllers\\BrandController::changeStatus\/$1"},{"method":"POST","route":"admin\/brands\/bulk_action\/(.*)","handler":"\\Admin\\Controllers\\BrandController::bulk_action\/$1"},{"method":"POST","route":"admin\/brands\/update\/(.*)","handler":"\\Admin\\Controllers\\BrandController::update\/$1"},{"method":"POST","route":"admin\/brands\/delete\/(.*)","handler":"\\Admin\\Controllers\\BrandController::delete\/$1"},{"method":"POST","route":"admin\/coupon\/store","handler":"\\Admin\\Controllers\\Coupon::store"},{"method":"POST","route":"admin\/coupon\/change_status\/(.*)","handler":"\\Admin\\Controllers\\Coupon::changeStatus\/$1"},{"method":"POST","route":"admin\/coupon\/delete\/(.*)","handler":"\\Admin\\Controllers\\Coupon::delete\/$1"},{"method":"POST","route":"admin\/coupon\/bulk_action\/(.*)","handler":"\\Admin\\Controllers\\Coupon::bulk_action\/$1"},{"method":"POST","route":"admin\/blogs\/store","handler":"\\Admin\\Controllers\\BlogController::store"},{"method":"POST","route":"admin\/blogs\/change_status\/(.*)","handler":"\\Admin\\Controllers\\BlogController::changeStatus\/$1"},{"method":"POST","route":"admin\/blogs\/delete\/(.*)","handler":"\\Admin\\Controllers\\BlogController::delete\/$1"},{"method":"POST","route":"admin\/blogs\/bulk_action\/(.*)","handler":"\\Admin\\Controllers\\BlogController::bulk_action\/$1"},{"method":"POST","route":"admin\/faqs\/change_sort\/(.*)","handler":"\\Admin\\Controllers\\FaqsController::change_sort\/$1"},{"method":"POST","route":"admin\/faqs\/store","handler":"\\Admin\\Controllers\\FaqsController::store"},{"method":"POST","route":"admin\/faqs\/change_status\/(.*)","handler":"\\Admin\\Controllers\\FaqsController::changeStatus\/$1"},{"method":"POST","route":"admin\/faqs\/delete\/(.*)","handler":"\\Admin\\Controllers\\FaqsController::delete\/$1"},{"method":"POST","route":"admin\/faqs\/bulk_action\/(.*)","handler":"\\Admin\\Controllers\\FaqsController::bulk_action\/$1"},{"method":"POST","route":"admin\/faqs\/sortfaqs","handler":"\\Admin\\Controllers\\FaqsController::sortfaqs"},{"method":"POST","route":"admin\/payments\/change_sort\/(.*)","handler":"\\Admin\\Controllers\\PaymentsController::change_sort\/$1"},{"method":"POST","route":"admin\/payments\/store","handler":"\\Admin\\Controllers\\PaymentsController::store"},{"method":"POST","route":"admin\/payments\/change_status\/(.*)","handler":"\\Admin\\Controllers\\PaymentsController::changeStatus\/$1"},{"method":"POST","route":"admin\/payments\/delete\/(.*)","handler":"\\Admin\\Controllers\\PaymentsController::delete\/$1"},{"method":"POST","route":"admin\/payments\/bulk_action\/(.*)","handler":"\\Admin\\Controllers\\PaymentsController::bulk_action\/$1"},{"method":"POST","route":"admin\/payments\/sortpayments","handler":"\\Admin\\Controllers\\PaymentsController::sortpayments"},{"method":"POST","route":"admin\/users\/store","handler":"\\Admin\\Controllers\\UserController::store"},{"method":"POST","route":"admin\/users\/change_status\/(.*)","handler":"\\Admin\\Controllers\\UserController::changeStatus\/$1"},{"method":"POST","route":"admin\/users\/mail\/(.*)","handler":"\\Admin\\Controllers\\UserController::mail\/$1"},{"method":"POST","route":"admin\/users\/add_funds\/(.*)","handler":"\\Admin\\Controllers\\UserController::add_funds\/$1"},{"method":"POST","route":"admin\/users\/set_password\/(.*)","handler":"\\Admin\\Controllers\\UserController::set_password\/$1"},{"method":"POST","route":"admin\/users\/view_user\/(.*)","handler":"\\Admin\\Controllers\\UserController::view_user\/$1"},{"method":"POST","route":"admin\/users\/bulk_action\/(.*)","handler":"\\Admin\\Controllers\\UserController::bulk_action\/$1"},{"method":"POST","route":"admin\/users\/delete\/(.*)","handler":"\\Admin\\Controllers\\UserController::delete\/$1"},{"method":"POST","route":"admin\/staffs\/store","handler":"\\Admin\\Controllers\\StaffController::store"},{"method":"POST","route":"admin\/staffs\/change_status\/(.*)","handler":"\\Admin\\Controllers\\StaffController::changeStatus\/$1"},{"method":"POST","route":"admin\/staffs\/mail\/(.*)","handler":"\\Admin\\Controllers\\StaffController::mail\/$1"},{"method":"POST","route":"admin\/staffs\/add_funds\/(.*)","handler":"\\Admin\\Controllers\\StaffController::add_funds\/$1"},{"method":"POST","route":"admin\/staffs\/set_password\/(.*)","handler":"\\Admin\\Controllers\\StaffController::set_password\/$1"},{"method":"POST","route":"admin\/staffs\/view_user\/(.*)","handler":"\\Admin\\Controllers\\StaffController::view_user\/$1"},{"method":"POST","route":"admin\/staffs\/bulk_action\/(.*)","handler":"\\Admin\\Controllers\\StaffController::bulk_action\/$1"},{"method":"POST","route":"admin\/staffs\/delete\/(.*)","handler":"\\Admin\\Controllers\\StaffController::delete\/$1"},{"method":"POST","route":"admin\/staffs\/role_permision\/(.*)\/(.*)","handler":"\\Admin\\Controllers\\StaffController::role_permision\/$1\/$2"},{"method":"POST","route":"admin\/staffs\/role_permision\/(.*)","handler":"\\Admin\\Controllers\\StaffController::role_permision\/$1"},{"method":"POST","route":"admin\/view-transaction\/(.*)\/(.*)","handler":"\\Admin\\Controllers\\Transactions::trxView\/$1\/$2"},{"method":"POST","route":"admin\/transactions\/add-sms","handler":"\\Admin\\Controllers\\Transactions::addSms"},{"method":"POST","route":"invoice\/(.*)","handler":"\\Home\\Controllers\\HomeController::invoice\/$1"}]},"badgeValue":125,"isEmpty":false,"hasTabContent":true,"hasLabel":false,"icon":"data:image\/png;base64,iVBORw0KGgoAAAANSUhEUgAAABgAAAAYCAYAAADgdz34AAAAAXNSR0IArs4c6QAAAARnQU1BAACxjwv8YQUAAAAJcEhZcwAADsMAAA7DAcdvqGQAAAFDSURBVEhL7ZRNSsNQFIUjVXSiOFEcuQIHDpzpxC0IGYeE\/BEInbWlCHEDLsSiuANdhKDjgm6ggtSJ+l25ldrmmTwIgtgDh\/t37r1J+16cX0dRFMtpmu5pWAkrvYjjOB7AETzStBFW+inxu3KUJMmhludQpoflS1zXban4LYqiO224h6VLTHr8Z+z8EpIHFF9gG78nDVmW7UgTHKjsCyY98QP+pcq+g8Ku2s8G8X3f3\/I8b038WZTp+bO38zxfFd+I6YY6sNUvFlSDk9CRhiAI1jX1I9Cfw7GG1UB8LAuwbU0ZwQnbRDeEN5qqBxZMLtE1ti9LtbREnMIuOXnyIf5rGIb7Wq8HmlZgwYBH7ORTcKH5E4mpjeGt9fBZcHE2GCQ3Vt7oTNPNg+FXLHnSsHkw\/FR+Gg2bB8Ptzrst\/v6C\/wrH+QB+duli6MYJdQAAAABJRU5ErkJggg==","hasTimelineData":false,"timelineData":[]},{"title":"Events","titleSafe":"events","titleDetails":"","display":{"events":{"pre_system":{"event":"pre_system","duration":"0.52","count":1},"dbquery":{"event":"dbquery","duration":"0.07","count":13},"post_controller_constructor":{"event":"post_controller_constructor","duration":"0.12","count":1}}},"badgeValue":15,"isEmpty":false,"hasTabContent":true,"hasLabel":false,"icon":"data:image\/png;base64,iVBORw0KGgoAAAANSUhEUgAAABgAAAAYCAYAAADgdz34AAAAAXNSR0IArs4c6QAAAARnQU1BAACxjwv8YQUAAAAJcEhZcwAADsMAAA7DAcdvqGQAAAEASURBVEhL7ZXNDcIwDIVTsRBH1uDQDdquUA6IM1xgCA6MwJUN2hk6AQzAz0vl0ETUxC5VT3zSU5w81\/mRMGZysixbFEVR0jSKNt8geQU9aRpFmp\/keX6AbjZ5oB74vsaN5lSzA4tLSjpBFxsjeSuRy4d2mDdQTWU7YLbXTNN05mKyovj5KL6B7q3hoy3KwdZxBlT+Ipz+jPHrBqOIynZgcZonoukb\/0ckiTHqNvDXtXEAaygRbaB9FvUTjRUHsIYS0QaSp+Dw6wT4hiTmYHOcYZsdLQ2CbXa4ftuuYR4x9vYZgdb4vsFYUdmABMYeukK9\/SUme3KMFQ77+Yfzh8eYF8+orDuDWU5LAAAAAElFTkSuQmCC","hasTimelineData":true,"timelineData":[{"name":"Event: pre_system","component":"Events","start":1721926181.6195280551910400390625,"duration":0.00051784515380859375},{"name":"Event: dbquery","component":"Events","start":1721926181.62423801422119140625,"duration":9.059906005859375e-6},{"name":"Event: dbquery","component":"Events","start":1721926181.624546051025390625,"duration":5.0067901611328125e-6},{"name":"Event: dbquery","component":"Events","start":1721926181.624721050262451171875,"duration":4.0531158447265625e-6},{"name":"Event: post_controller_constructor","component":"Events","start":1721926181.6247479915618896484375,"duration":0.0001161098480224609375},{"name":"Event: dbquery","component":"Events","start":1721926181.6251699924468994140625,"duration":5.9604644775390625e-6},{"name":"Event: dbquery","component":"Events","start":1721926181.6253659725189208984375,"duration":5.0067901611328125e-6},{"name":"Event: dbquery","component":"Events","start":1721926181.625586032867431640625,"duration":5.0067901611328125e-6},{"name":"Event: dbquery","component":"Events","start":1721926181.6257240772247314453125,"duration":5.0067901611328125e-6},{"name":"Event: dbquery","component":"Events","start":1721926181.6258900165557861328125,"duration":5.0067901611328125e-6},{"name":"Event: dbquery","component":"Events","start":1721926181.6260640621185302734375,"duration":5.0067901611328125e-6},{"name":"Event: dbquery","component":"Events","start":1721926181.62623310089111328125,"duration":5.0067901611328125e-6},{"name":"Event: dbquery","component":"Events","start":1721926181.6263821125030517578125,"duration":3.814697265625e-6},{"name":"Event: dbquery","component":"Events","start":1721926181.6265261173248291015625,"duration":3.814697265625e-6},{"name":"Event: dbquery","component":"Events","start":1721926181.62666797637939453125,"duration":4.0531158447265625e-6}]}],"vars":{"varData":{"View Data":{"items":"<div class=\"kint-rich\"><dl><dt class=\"kint-parent\"><span class=\"kint-popup-trigger\" title=\"Open in new window\">&boxbox;<\/span><span class=\"kint-search-trigger\" title=\"Show search box\">&telrec;<\/span><input type=\"text\" class=\"kint-search\" value=\"\"><nav><\/nav><dfn>$value<\/dfn> <var>array<\/var> (34)<\/dt><dd><dl><dt><span class=\"kint-access-path-trigger\" title=\"Show access path\">&rlarr;<\/span><dfn>invoice_ids<\/dfn> =&gt; <var>string<\/var> (32) \"2582570763da373a4af814500b51181f\"<div class=\"access-path\">$value['invoice_ids']<\/div><\/dt><\/dl><dl><dt><span class=\"kint-access-path-trigger\" title=\"Show access path\">&rlarr;<\/span><dfn>id<\/dfn> =&gt; <var>string<\/var> (1) \"1\"<div class=\"access-path\">$value['id']<\/div><\/dt><\/dl><dl><dt><span class=\"kint-access-path-trigger\" title=\"Show access path\">&rlarr;<\/span><dfn>ids<\/dfn> =&gt; <var>string<\/var> (32) \"d9f78560d58871116c7a7145e492968b\"<div class=\"access-path\">$value['ids']<\/div><\/dt><\/dl><dl><dt><span class=\"kint-access-path-trigger\" title=\"Show access path\">&rlarr;<\/span><dfn>uid<\/dfn> =&gt; <var>string<\/var> (1) \"1\"<div class=\"access-path\">$value['uid']<\/div><\/dt><\/dl><dl><dt><span class=\"kint-access-path-trigger\" title=\"Show access path\">&rlarr;<\/span><dfn>customer_name<\/dfn> =&gt; <var>string<\/var> (5) \"Hosen\"<div class=\"access-path\">$value['customer_name']<\/div><\/dt><\/dl><dl><dt><span class=\"kint-access-path-trigger\" title=\"Show access path\">&rlarr;<\/span><dfn>customer_number<\/dfn> =&gt; <var>string<\/var> (11) \"01933110972\"<div class=\"access-path\">$value['customer_number']<\/div><\/dt><\/dl><dl><dt><span class=\"kint-access-path-trigger\" title=\"Show access path\">&rlarr;<\/span><dfn>customer_amount<\/dfn> =&gt; <var>string<\/var> (3) \"500\"<div class=\"access-path\">$value['customer_amount']<\/div><\/dt><\/dl><dl><dt><span class=\"kint-access-path-trigger\" title=\"Show access path\">&rlarr;<\/span><dfn>customer_email<\/dfn> =&gt; <var>string<\/var> (25) \"hosentechnology@gmail.com\"<div class=\"access-path\">$value['customer_email']<\/div><\/dt><\/dl><dl><dt><span class=\"kint-access-path-trigger\" title=\"Show access path\">&rlarr;<\/span><dfn>customer_address<\/dfn> =&gt; <var>string<\/var> (6) \"112233\"<div class=\"access-path\">$value['customer_address']<\/div><\/dt><\/dl><dl><dt><span class=\"kint-access-path-trigger\" title=\"Show access path\">&rlarr;<\/span><dfn>customer_description<\/dfn> =&gt; <var>string<\/var> (6) \"112233\"<div class=\"access-path\">$value['customer_description']<\/div><\/dt><\/dl><dl><dt><span class=\"kint-access-path-trigger\" title=\"Show access path\">&rlarr;<\/span><dfn>status<\/dfn> =&gt; <var>string<\/var> (1) \"1\"<div class=\"access-path\">$value['status']<\/div><\/dt><\/dl><dl><dt><span class=\"kint-access-path-trigger\" title=\"Show access path\">&rlarr;<\/span><dfn>pay_status<\/dfn> =&gt; <var>string<\/var> (1) \"0\"<div class=\"access-path\">$value['pay_status']<\/div><\/dt><\/dl><dl><dt><span class=\"kint-access-path-trigger\" title=\"Show access path\">&rlarr;<\/span><dfn>brand_id<\/dfn> =&gt; <var>string<\/var> (1) \"1\"<div class=\"access-path\">$value['brand_id']<\/div><\/dt><\/dl><dl><dt><span class=\"kint-access-path-trigger\" title=\"Show access path\">&rlarr;<\/span><dfn>transaction_id<\/dfn> =&gt; <var>null<\/var><div class=\"access-path\">$value['transaction_id']<\/div><\/dt><\/dl><dl><dt><span class=\"kint-access-path-trigger\" title=\"Show access path\">&rlarr;<\/span><dfn>extras<\/dfn> =&gt; <var>null<\/var><div class=\"access-path\">$value['extras']<\/div><\/dt><\/dl><dl><dt><span class=\"kint-access-path-trigger\" title=\"Show access path\">&rlarr;<\/span><dfn>created_at<\/dfn> =&gt; <var>string<\/var> (19) \"2024-07-13 22:58:15\"<div class=\"access-path\">$value['created_at']<\/div><\/dt><\/dl><dl><dt><span class=\"kint-access-path-trigger\" title=\"Show access path\">&rlarr;<\/span><dfn>deleted_at<\/dfn> =&gt; <var>null<\/var><div class=\"access-path\">$value['deleted_at']<\/div><\/dt><\/dl><dl><dt><span class=\"kint-access-path-trigger\" title=\"Show access path\">&rlarr;<\/span><dfn>user_id<\/dfn> =&gt; <var>string<\/var> (1) \"1\"<div class=\"access-path\">$value['user_id']<\/div><\/dt><\/dl><dl><dt><span class=\"kint-access-path-trigger\" title=\"Show access path\">&rlarr;<\/span><dfn>email<\/dfn> =&gt; <var>string<\/var> (25) \"hosentechnology@gmail.com\"<div class=\"access-path\">$value['email']<\/div><\/dt><\/dl><dl><dt><span class=\"kint-access-path-trigger\" title=\"Show access path\">&rlarr;<\/span><dfn>password<\/dfn> =&gt; <var>string<\/var> (60) \"$2y$10$AlSS3ncG5ZhqhNFRtpJubu2IUCbZgaRW046suAUftIDW0A\/EXLhNS\"<div class=\"access-path\">$value['password']<\/div><\/dt><\/dl><dl><dt><span class=\"kint-access-path-trigger\" title=\"Show access path\">&rlarr;<\/span><dfn>first_name<\/dfn> =&gt; <var>string<\/var> (5) \"Hosen\"<div class=\"access-path\">$value['first_name']<\/div><\/dt><\/dl><dl><dt><span class=\"kint-access-path-trigger\" title=\"Show access path\">&rlarr;<\/span><dfn>last_name<\/dfn> =&gt; <var>string<\/var> (10) \"Technology\"<div class=\"access-path\">$value['last_name']<\/div><\/dt><\/dl><dl><dt><span class=\"kint-access-path-trigger\" title=\"Show access path\">&rlarr;<\/span><dfn>phone<\/dfn> =&gt; <var>string<\/var> (11) \"01933110972\"<div class=\"access-path\">$value['phone']<\/div><\/dt><\/dl><dl><dt><span class=\"kint-access-path-trigger\" title=\"Show access path\">&rlarr;<\/span><dfn>balance<\/dfn> =&gt; <var>string<\/var> (7) \"100.000\"<div class=\"access-path\">$value['balance']<\/div><\/dt><\/dl><dl><dt><span class=\"kint-access-path-trigger\" title=\"Show access path\">&rlarr;<\/span><dfn>more_information<\/dfn> =&gt; <var>null<\/var><div class=\"access-path\">$value['more_information']<\/div><\/dt><\/dl><dl><dt><span class=\"kint-access-path-trigger\" title=\"Show access path\">&rlarr;<\/span><dfn>avatar<\/dfn> =&gt; <var>null<\/var><div class=\"access-path\">$value['avatar']<\/div><\/dt><\/dl><dl><dt><span class=\"kint-access-path-trigger\" title=\"Show access path\">&rlarr;<\/span><dfn>api_credentials<\/dfn> =&gt; <var>null<\/var><div class=\"access-path\">$value['api_credentials']<\/div><\/dt><\/dl><dl><dt><span class=\"kint-access-path-trigger\" title=\"Show access path\">&rlarr;<\/span><dfn>timezone<\/dfn> =&gt; <var>null<\/var><div class=\"access-path\">$value['timezone']<\/div><\/dt><\/dl><dl><dt><span class=\"kint-access-path-trigger\" title=\"Show access path\">&rlarr;<\/span><dfn>ref_id<\/dfn> =&gt; <var>string<\/var> (1) \"0\"<div class=\"access-path\">$value['ref_id']<\/div><\/dt><\/dl><dl><dt><span class=\"kint-access-path-trigger\" title=\"Show access path\">&rlarr;<\/span><dfn>ref_key<\/dfn> =&gt; <var>string<\/var> (32) \"c3573707b944f58ad4e520c65b24dab9\"<div class=\"access-path\">$value['ref_key']<\/div><\/dt><\/dl><dl><dt><span class=\"kint-access-path-trigger\" title=\"Show access path\">&rlarr;<\/span><dfn>addons<\/dfn> =&gt; <var>null<\/var><div class=\"access-path\">$value['addons']<\/div><\/dt><\/dl><dl><dt><span class=\"kint-access-path-trigger\" title=\"Show access path\">&rlarr;<\/span><dfn>activation_key<\/dfn> =&gt; <var>string<\/var> (25) \"sixtpr3t4pl5Y0ZkNmwHwrUbu\"<div class=\"access-path\">$value['activation_key']<\/div><\/dt><\/dl><dl><dt class=\"kint-parent\"><span class=\"kint-access-path-trigger\" title=\"Show access path\">&rlarr;<\/span><span class=\"kint-popup-trigger\" title=\"Open in new window\">&boxbox;<\/span><nav><\/nav><dfn>reset_key<\/dfn> =&gt; <var>string<\/var> (32) \"1ZsT1SpEuCKIYHazRmkFARmV9Pi9W7Nt\"<div class=\"access-path\">$value['reset_key']<\/div><\/dt><dd><ul class=\"kint-tabs\"><li class=\"kint-active-tab\">Base64<\/li><\/ul><ul class=\"kint-tab-contents\"><li class=\"kint-show\"><dl><dt><span class=\"kint-access-path-trigger\" title=\"Show access path\">&rlarr;<\/span><dfn>base64_decode(reset_key)<\/dfn> <var>binary string<\/var> (24)<div class=\"access-path\">base64_decode($value['reset_key'])<\/div><\/dt><\/dl><\/li><\/ul><\/dd><\/dl><dl><dt><span class=\"kint-access-path-trigger\" title=\"Show access path\">&rlarr;<\/span><dfn>updated_at<\/dfn> =&gt; <var>string<\/var> (19) \"2024-07-13 22:58:15\"<div class=\"access-path\">$value['updated_at']<\/div><\/dt><\/dl><\/dd><\/dl><\/div>"}},"headers":{"Accept":"text\/html,application\/xhtml+xml,application\/xml;q=0.9,image\/avif,image\/webp,image\/apng,*\/*;q=0.8,application\/signed-exchange;v=b3;q=0.7","Accept-Encoding":"gzip, br","Accept-Language":"en-BD,en-GB;q=0.9,en-US;q=0.8,en;q=0.7,bn;q=0.6,tr;q=0.5","Connection":"Keep-Alive","Cookie":"token=25f94b567a6b14c6f8c9f6651a92d311; ci_session=62818998ed6a5049ca6b5a281fecad263d0c5c88","Host":"bdautopay.com","Referer":"https:\/\/bdautopay.com\/invoice\/2582570763da373a4af814500b51181f","User-Agent":"Mozilla\/5.0 (Linux; Android 10; K) AppleWebKit\/537.36 (KHTML, like Gecko) Chrome\/127.0.0.0 Mobile Safari\/537.36","Cache-Control":"max-age=0","X-Forwarded-For":"103.179.15.34","Cf-Ray":"8a8da4cb19d47c45-DAC","X-Forwarded-Proto":"https","Cf-Visitor":"{&quot;scheme&quot;:&quot;https&quot;}","Sec-Ch-Ua":"&quot;Not)A;Brand&quot;;v=&quot;99&quot;, &quot;Google Chrome&quot;;v=&quot;127&quot;, &quot;Chromium&quot;;v=&quot;127&quot;","Sec-Ch-Ua-Mobile":"?1","Sec-Ch-Ua-Platform":"&quot;Android&quot;","Upgrade-Insecure-Requests":"1","Sec-Fetch-Site":"same-origin","Sec-Fetch-Mode":"navigate","Sec-Fetch-User":"?1","Sec-Fetch-Dest":"document","Priority":"u=0, i","Cf-Connecting-Ip":"103.179.15.34","Cdn-Loop":"cloudflare","Cf-Ipcountry":"BD"},"cookies":{"token":"25f94b567a6b14c6f8c9f6651a92d311","ci_session":"62818998ed6a5049ca6b5a281fecad263d0c5c88"},"request":"HTTPS\/1.1","response":{"statusCode":200,"reason":"OK","contentType":"text\/html; charset=UTF-8","headers":{"Cache-Control":"no-store, max-age=0, no-cache","Content-Type":"text\/html; charset=UTF-8"}}},"config":{"ciVersion":"4.4.3","phpVersion":"7.4.33","phpSAPI":"litespeed","environment":"development","baseURL":"https:\/\/bdautopay.com","timezone":"Asia\/Dhaka","locale":"en","cspEnabled":false}}